Workbook

Sheet RESUMO
A1: MARCAS | H1: De | I1: Até | J1: Frete | K1: Valor min | L1: Valor Max
A2: BOMBER | C2: PREÇO DE VENDA | D2: 599 | H2: 0 | I2: 0.3 | J2: 11.97 | K2: 79 | L2: 99.99
A3: POSITIVO | H3: 0.3 | I3: 0.5 | J3: 12.87 | K3: 79 | L3: 99.99
A4: BRASTEMP | C4: COMISSÃO | D4: 0.1 | E4: =D2*D4 -> 59.9 | H4: 0.5 | I4: 1 | J4: 13.47 | K4: 79 | L4: 99.99
A5: VENTISOL | C5: FRETE | D5: =D2*5% -> 29.95 | E5: =D5 -> 29.95 | H5: 1 | I5: 2 | J5: 14.07 | K5: 79 | L5: 99.99
A6: AOC | C6: EMBALAGEM | D6: 0 | E6: =D6 -> 0 | H6: 2 | I6: 3 | J6: 14.97 | K6: 79 | L6: 99.99
A7: PHILIPS | C7: MAGIS | D7: 0 | E7: =D7 -> 0 | H7: 3 | I7: 4 | J7: 16.17 | K7: 79 | L7: 99.99
A8: LG | C8: FINANCEIRO | D8: 0 | E8: =D21*D8 -> 0 | H8: 4 | I8: 5 | J8: 17.07 | K8: 79 | L8: 99.99
A9: EFL | C9: IMPOSTO + CUSTO FIXO | D9: 0 | E9: =D9*D2 -> 0 | H9: 5 | I9: 9 | J9: 26.67 | K9: 79 | L9: 99.99
A10: THUNDEROBOT | C10: COMISSÃO | D10: 0 | E10: =D10*D21 -> 0 | H10: 9 | I10: 13 | J10: 39.57 | K10: 79 | L10: 99.99
A11: DAZZ | C11: REBATE | D11: 0 | E11: 0 | H11: 13 | I11: 17 | J11: 44.07 | K11: 79 | L11: 99.99
A12: MAXPRINT | C12: INDICE DE RMA | D12: 0 | E12: =D21*D12 -> 0 | H12: 0 | I12: 0.3 | J12: 13.97 | K12: 100 | L12: 119.99
A13: MONDIAL | C13: COLETA | D13: 0 | E13: =D13*D21 -> 0 | H13: 0.3 | I13: 0.5 | J13: 15.01 | K13: 100 | L13: 119.99
A14: AMAZON | H14: 0.5 | I14: 1 | J14: 15.71 | K14: 100 | L14: 119.99
A15: BRITANIA | C15: VALOR LIQUIDO | D15: =D2-E4-D5-D6-D7-E8-E9-E10-E12-E11+D11 -> 509.15 | H15: 1 | I15: 2 | J15: 16.41 | K15: 100 | L15: 119.99
A16: TARGUS | C16: MARGEM VALOR | D16: =D15-D21 -> 210.15 | E16: =D16*50 -> 10507.5 | H16: 2 | I16: 3 | J16: 17.47 | K16: 100 | L16: 119.99
A17: MALLORY | C17: MARGEM DA VENDA | D17: =D16/D2 -> 0.35083472 | E17: =D16 -> 210.15 | H17: 3 | I17: 4 | J17: 18.87 | K17: 100 | L17: 119.99
A18: COLORMAQ | C18: MARGEM LIQUIDA | D18: =D16/D21 -> 0.70284281 | H18: 4 | I18: 5 | J18: 19.92 | K18: 100 | L18: 119.99
A19: PHILCO | H19: 5 | I19: 9 | J19: 31.12 | K19: 100 | L19: 119.99
A20: VAIO | H20: 9 | I20: 13 | J20: 46.17 | K20: 100 | L20: 119.99
A21: FISCHER | C21: CUSTO | D21: 299 | E21: =D21*1.2 -> 358.8 | H21: 13 | I21: 17 | J21: 51.42 | K21: 100 | L21: 119.99
A22: INSTA360 | D22: 3 | H22: 17 | I22: 23 | J22: 60.17 | K22: 100 | L22: 119.99
A23: TAIFF | C23: CUSTO IDEAL | D23: =D15*0.8 -> 407.32 | H23: 0 | I23: 0.3 | J23: 15.96 | K23: 120 | L23: 149.99
A24: MIDEA | H24: 0.3 | I24: 0.5 | J24: 17.16 | K24: 120 | L24: 149.99
A25: CONSUL | H25: 0.5 | I25: 1 | J25: 17.95 | K25: 120 | L25: 149.99
A26: NAUTIKA | H26: 1 | I26: 2 | J26: 18.76 | K26: 120 | L26: 149.99
A27: ECOFLEX | H27: 2 | I27: 3 | J27: 19.96 | K27: 120 | L27: 149.99
A28: GAZIN | H28: 3 | I28: 4 | J28: 21.56 | K28: 120 | L28: 149.99
A29: BLACKDECKER | H29: 4 | I29: 5 | J29: 22.76 | K29: 120 | L29: 149.99
A30: SEMP | H30: 5 | I30: 9 | J30: 35.56 | K30: 120 | L30: 149.99
H31: 9 | I31: 13 | J31: 52.76 | K31: 120 | L31: 149.99
H32: 13 | I32: 17 | J32: 58.76 | K32: 120 | L32: 149.99
H33: 17 | I33: 23 | J33: 68.76 | K33: 120 | L33: 149.99
H34: 23 | I34: 30 | J34: 79.16 | K34: 120 | L34: 149.99
H35: 0 | I35: 0.3 | J35: 17.95 | K35: 150 | L35: 199.99
H36: 0.3 | I36: 0.5 | J36: 19.3 | K36: 150 | L36: 199.99
H37: 0.5 | I37: 1 | J37: 20.2 | K37: 150 | L37: 199.99
H38: 1 | I38: 2 | J38: 21.1 | K38: 150 | L38: 199.99
H39: 2 | I39: 3 | J39: 22.45 | K39: 150 | L39: 199.99
H40: 3 | I40: 4 | J40: 24.25 | K40: 150 | L40: 199.99
H41: 4 | I41: 5 | J41: 25.6 | K41: 150 | L41: 199.99
H42: 5 | I42: 9 | J42: 40 | K42: 150 | L42: 199.99
... H69: 150 | I69: 300 | J69: 249.45 | K69: 200 | L69: 49999

Sheet INIST
A1: MARCA | B1: SKU | C1: CUSTO | D1: PEMI | E1: IMPOSTO | F1: VERBA | G1: AUTO | H1: CLASSICO | I1: COMISSÃO | J1: FRETE | K1: PROMO | L1: MARGEM | M1: PREMIUM | N1: COMISSAO | O1: FRETE | P1: PROMO | Q1: MARGEM
A2: PHILCO | B2: PHILCO-PAS26P-BIV | C2: 499.43 | D2: 4 | E2: 0.04 | F2: 0 | G2: 2 | H2: 575 | I2: 0.11 | J2: {=IF(H2<12.5, H2/2, IF(H2<29, 6.25, IF(H2<50, 6.5, IF(H2<79, 6.75, VALUE(SUBSTITUTE( INDEX(RESUMO!$J$2:$J$100, MATCH(1, (D2>=RESUMO!$H$2:$H$100)*(D2<=RESUMO!$I$2:$I$100)*(H2>=RESUMO!$K$2:$K$100)*(H2<=RESUMO!$L$2:$L$100), 0)), "R$ ", "")) ))))} -> 26.95 | K2: 0 | L2: =S2/H2 -> -0.060186435 | M2: 709.25 | N2: 0.16 | O2: {=IF(M2<12.5, 0, IF(M2<29, 6.25, IF(M2<50, 6.5, IF(M2<79, 6.75, VALUE(SUBSTITUTE( INDEX(RESUMO!$J$2:$J$100, MATCH(1, (D2>=RESUMO!$H$2:$H$100)*(D2<=RESUMO!$I$2:$I$100)*(M2>=RESUMO!$K$2:$K$100)*(M2<=RESUMO!$L$2:$L$100), 0)), "R$ ", "")) ))))} -> 26.95 | P2: 0 | Q2: =U2/M2 -> 0.069669087 | R2: =(H2-(H2*I2)-J2-(C2*E2)+K2) -> 464.8228 | S2: =R2-(C2-F2) -> -34.6072 | T2: =(M2-(M2*N2)-O2-(C2*E2)+P2) -> 548.8428 | U2: =T2-(C2-F2) -> 49.4128
A3: BRITANIA | B3: BRITANIA-BAS1500V-220V | C3: 130.51 | D3: 2 | E3: 0.04 | F3: 0 | G3: 2 | H3: 187.5 | I3: 0.11 | J3: {=IF(H3<12.5, H3/2, IF(H3<29, 6.25, IF(H3<50, 6.5, IF(H3<79, 6.75, VALUE(SUBSTITUTE( INDEX(RESUMO!$J$2:$J$100, MATCH(1, (D3>=RESUMO!$H$2:$H$100)*(D3<=RESUMO!$I$2:$I$100)*(H3>=RESUMO!$K$2:$K$100)*(H3<=RESUMO!$L$2:$L$100), 0)), "R$ ", "")) ))))} -> 21.1 | K3: 0 | L3: =S3/H3 -> 0.0535712 | M3: 199.9 | N3: 0.16 | O3: {=IF(M3<12.5, 0, IF(M3<29, 6.25, IF(M3<50, 6.5, IF(M3<79, 6.75, VALUE(SUBSTITUTE( INDEX(RESUMO!$J$2:$J$100, MATCH(1, (D3>=RESUMO!$H$2:$H$100)*(D3<=RESUMO!$I$2:$I$100)*(M3>=RESUMO!$K$2:$K$100)*(M3<=RESUMO!$L$2:$L$100), 0)), "R$ ", "")) ))))} -> 21.1 | P3: 0 | Q3: =U3/M3 -> 0.055455728 | R3: =(H3-(H3*I3)-J3-(C3*E3)+K3) -> 140.5546 | S3: =R3-(C3-F3) -> 10.0446 | T3: =(M3-(M3*N3)-O3-(C3*E3)+P3) -> 141.5956 | U3: =T3-(C3-F3) -> 11.0856
A4: BRITANIA | B4: BRITANIA-JUI1000-127V | C4: 328.42 | D4: 9 | E4: 0.04 | F4: 0 | G4: 2 | H4: 403 | I4: 0.11 | J4: {=IF(H4<12.5, H4/2, IF(H4<29, 6.25, IF(H4<50, 6.5, IF(H4<79, 6.75, VALUE(SUBSTITUTE( INDEX(RESUMO!$J$2:$J$100, MATCH(1, (D4>=RESUMO!$H$2:$H$100)*(D4<=RESUMO!$I$2:$I$100)*(H4>=RESUMO!$K$2:$K$100)*(H4<=RESUMO!$L$2:$L$100), 0)), "R$ ", "")) ))))} -> 44.45 | K4: 19.2 | L4: =S4/H4 -> -0.020190571 | M4: 449.9 | N4: 0.16 | O4: {=IF(M4<12.5, 0, IF(M4<29, 6.25, IF(M4<50, 6.5, IF(M4<79, 6.75, VALUE(SUBSTITUTE( INDEX(RESUMO!$J$2:$J$100, MATCH(1, (D4>=RESUMO!$H$2:$H$100)*(D4<=RESUMO!$I$2:$I$100)*(M4>=RESUMO!$K$2:$K$100)*(M4<=RESUMO!$L$2:$L$100), 0)), "R$ ", "")) ))))} -> 44.45 | P4: 26.99 | Q4: =U4/M4 -> 0.042007557 | R4: =(H4-(H4*I4)-J4-(C4*E4)+K4) -> 320.2832 | S4: =R4-(C4-F4) -> -8.1368 | T4: =(M4-(M4*N4)-O4-(C4*E4)+P4) -> 347.3192 | U4: =T4-(C4-F4) -> 18.8992
A5: PHILCO | B5: PHILCO-PFE36S-220V | C5: 763.58 | D5: 13 | E5: 0.04 | F5: 0 | G5: 2 | H5: 1024.9 | I5: 0.11 | J5: {=IF(H5<12.5, H5/2, IF(H5<29, 6.25, IF(H5<50, 6.5, IF(H5<79, 6.75, VALUE(SUBSTITUTE( INDEX(RESUMO!$J$2:$J$100, MATCH(1, (D5>=RESUMO!$H$2:$H$100)*(D5<=RESUMO!$I$2:$I$100)*(H5>=RESUMO!$K$2:$K$100)*(H5<=RESUMO!$L$2:$L$100), 0)), "R$ ", "")) ))))} -> 65.95 | K5: 0 | L5: =S5/H5 -> 0.050822324 | M5: 1089.9 | N5: 0.16 | O5: {=IF(M5<12.5, 0, IF(M5<29, 6.25, IF(M5<50, 6.5, IF(M5<79, 6.75, VALUE(SUBSTITUTE( INDEX(RESUMO!$J$2:$J$100, MATCH(1, (D5>=RESUMO!$H$2:$H$100)*(D5<=RESUMO!$I$2:$I$100)*(M5>=RESUMO!$K$2:$K$100)*(M5<=RESUMO!$L$2:$L$100), 0)), "R$ ", "")) ))))} -> 65.95 | P5: 0 | Q5: =U5/M5 -> 0.050869621 | R5: =(H5-(H5*I5)-J5-(C5*E5)+K5) -> 815.6678 | S5: =R5-(C5-F5) -> 52.0878 | T5: =(M5-(M5*N5)-O5-(C5*E5)+P5) -> 819.0228 | U5: =T5-(C5-F5) -> 55.4428
A6: PHILCO | B6: PHILCO-NANO-CERAN-T-220V | C6: 124.4 | D6: 2 | E6: 0.04 | F6: 0 | G6: 2 | H6: 179.9 | I6: 0.11 | J6: {=IF(H6<12.5, H6/2, IF(H6<29, 6.25, IF(H6<50, 6.5, IF(H6<79, 6.75, VALUE(SUBSTITUTE( INDEX(RESUMO!$J$2:$J$100, MATCH(1, (D6>=RESUMO!$H$2:$H$100)*(D6<=RESUMO!$I$2:$I$100)*(H6>=RESUMO!$K$2:$K$100)*(H6<=RESUMO!$L$2:$L$100), 0)), "R$ ", "")) ))))} -> 21.1 | K6: 0 | L6: =S6/H6 -> 0.053557532 | M6: 191.5 | N6: 0.16 | O6: {=IF(M6<12.5, 0, IF(M6<29, 6.25, IF(M6<50, 6.5, IF(M6<79, 6.75, VALUE(SUBSTITUTE( INDEX(RESUMO!$J$2:$J$100, MATCH(1, (D6>=RESUMO!$H$2:$H$100)*(D6<=RESUMO!$I$2:$I$100)*(M6>=RESUMO!$K$2:$K$100)*(M6<=RESUMO!$L$2:$L$100), 0)), "R$ ", "")) ))))} -> 21.1 | P6: 0 | Q6: =U6/M6 -> 0.054224543 | R6: =(H6-(H6*I6)-J6-(C6*E6)+K6) -> 134.035 | S6: =R6-(C6-F6) -> 9.635 | T6: =(M6-(M6*N6)-O6-(C6*E6)+P6) -> 134.784 | U6: =T6-(C6-F6) -> 10.384
A7: PHILCO | B7: PHILCO-PTV32M9GACGB-127V | C7: 883.54 | D7: 9 | E7: 0.04 | F7: 40.41 | G7: 2 | H7: 995 | I7: 0.11 | J7: {=IF(H7<12.5, H7/2, IF(H7<29, 6.25, IF(H7<50, 6.5, IF(H7<79, 6.75, VALUE(SUBSTITUTE( INDEX(RESUMO!$J$2:$J$100, MATCH(1, (D7>=RESUMO!$H$2:$H$100)*(D7<=RESUMO!$I$2:$I$100)*(H7>=RESUMO!$K$2:$K$100)*(H7<=RESUMO!$L$2:$L$100), 0)), "R$ ", "")) ))))} -> 44.45 | K7: 0 | L7: =S7/H7 -> -0.037559397 | M7: 1099 | N7: 0.16 | O7: {=IF(M7<12.5, 0, IF(M7<29, 6.25, IF(M7<50, 6.5, IF(M7<79, 6.75, VALUE(SUBSTITUTE( INDEX(RESUMO!$J$2:$J$100, MATCH(1, (D7>=RESUMO!$H$2:$H$100)*(D7<=RESUMO!$I$2:$I$100)*(M7>=RESUMO!$K$2:$K$100)*(M7<=RESUMO!$L$2:$L$100), 0)), "R$ ", "")) ))))} -> 44.45 | P7: 0 | Q7: =U7/M7 -> 0.00021692448 | R7: =(H7-(H7*I7)-J7-(C7*E7)+K7) -> 805.7584 | S7: =R7-(C7-F7) -> -37.3716 | T7: =(M7-(M7*N7)-O7-(C7*E7)+P7) -> 843.3684 | U7: =T7-(C7-F7) -> 0.2384
A8: BRITANIA | B8: BRITANIA-BFE25P-127V | C8: 363.46 | D8: 13 | E8: 0.04 | F8: 0 | G8: 2 | H8: 449.9 | I8: 0.11 | J8: {=IF(H8<12.5, H8/2, IF(H8<29, 6.25, IF(H8<50, 6.5, IF(H8<79, 6.75, VALUE(SUBSTITUTE( INDEX(RESUMO!$J$2:$J$100, MATCH(1, (D8>=RESUMO!$H$2:$H$100)*(D8<=RESUMO!$I$2:$I$100)*(H8>=RESUMO!$K$2:$K$100)*(H8<=RESUMO!$L$2:$L$100), 0)), "R$ ", "")) ))))} -> 65.95 | K8: 0 | L8: =S8/H8 -> -0.096771283 | M8: 565 | N8: 0.16 | O8: {=IF(M8<12.5, 0, IF(M8<29, 6.25, IF(M8<50, 6.5, IF(M8<79, 6.75, VALUE(SUBSTITUTE( INDEX(RESUMO!$J$2:$J$100, MATCH(1, (D8>=RESUMO!$H$2:$H$100)*(D8<=RESUMO!$I$2:$I$100)*(M8>=RESUMO!$K$2:$K$100)*(M8<=RESUMO!$L$2:$L$100), 0)), "R$ ", "")) ))))} -> 65.95 | P8: 0 | Q8: =U8/M8 -> 0.054250619 | R8: =(H8-(H8*I8)-J8-(C8*E8)+K8) -> 319.9226 | S8: =R8-(C8-F8) -> -43.5374 | T8: =(M8-(M8*N8)-O8-(C8*E8)+P8) -> 394.1116 | U8: =T8-(C8-F8) -> 30.6516
A9: BRITANIA | B9: BRITANIA-BFE25P-220V | C9: 363.46 | D9: 13 | E9: 0.04 | F9: 0 | G9: 2 | H9: 499 | I9: 0.11 | J9: {=IF(H9<12.5, H9/2, IF(H9<29, 6.25, IF(H9<50, 6.5, IF(H9<79, 6.75, VALUE(SUBSTITUTE( INDEX(RESUMO!$J$2:$J$100, MATCH(1, (D9>=RESUMO!$H$2:$H$100)*(D9<=RESUMO!$I$2:$I$100)*(H9>=RESUMO!$K$2:$K$100)*(H9<=RESUMO!$L$2:$L$100), 0)), "R$ ", "")) ))))} -> 65.95 | K9: 0 | L9: =S9/H9 -> 0.0003238477 | M9: 566 | N9: 0.16 | O9: {=IF(M9<12.5, 0, IF(M9<29, 6.25, IF(M9<50, 6.5, IF(M9<79, 6.75, VALUE(SUBSTITUTE( INDEX(RESUMO!$J$2:$J$100, MATCH(1, (D9>=RESUMO!$H$2:$H$100)*(D9<=RESUMO!$I$2:$I$100)*(M9>=RESUMO!$K$2:$K$100)*(M9<=RESUMO!$L$2:$L$100), 0)), "R$ ", "")) ))))} -> 65.95 | P9: 0 | Q9: =U9/M9 -> 0.055638869 | R9: =(H9-(H9*I9)-J9-(C9*E9)+K9) -> 363.6216 | S9: =R9-(C9-F9) -> 0.1616 | T9: =(M9-(M9*N9)-O9-(C9*E9)+P9) -> 394.9516 | U9: =T9-(C9-F9) -> 31.4916
A10: PHILCO | B10: PHILCO-PTE03-BIV | C10: 86.88 | D10: 0.3 | E10: 0.04 | F10: 0 | G10: 2 | H10: 130.5 | I10: 0.12 | J10: {=IF(H10<12.5, H10/2, IF(H10<29, 6.25, IF(H10<50, 6.5, IF(H10<79, 6.75, VALUE(SUBSTITUTE( INDEX(RESUMO!$J$2:$J$100, MATCH(1, (D10>=RESUMO!$H$2:$H$100)*(D10<=RESUMO!$I$2:$I$100)*(H10>=RESUMO!$K$2:$K$100)*(H10<=RESUMO!$L$2:$L$100), 0)), "R$ ", "")) ))))} -> 15.96 | K10: 0 | L10: =S10/H10 -> 0.065324138 | M10: 139.5 | N10: 0.17 | O10: {=IF(M10<12.5, 0, IF(M10<29, 6.25, IF(M10<50, 6.5, IF(M10<79, 6.75, VALUE(SUBSTITUTE( INDEX(RESUMO!$J$2:$J$100, MATCH(1, (D10>=RESUMO!$H$2:$H$100)*(D10<=RESUMO!$I$2:$I$100)*(M10>=RESUMO!$K$2:$K$100)*(M10<=RESUMO!$L$2:$L$100), 0)), "R$ ", "")) ))))} -> 15.96 | P10: 0 | Q10: =U10/M10 -> 0.067883871 | R10: =(H10-(H10*I10)-J10-(C10*E10)+K10) -> 95.4048 | S10: =R10-(C10-F10) -> 8.5248 | T10: =(M10-(M10*N10)-O10-(C10*E10)+P10) -> 96.3498 | U10: =T10-(C10-F10) -> 9.4698
A11: PHILCO | B11: PHILCO-PMB37EB-127V | C11: 1167.99 | D11: 23 | E11: 0.04 | F11: 0 | G11: 2 | H11: 1549.9 | I11: 0.11 | J11: {=IF(H11<12.5, H11/2, IF(H11<29, 6.25, IF(H11<50, 6.5, IF(H11<79, 6.75, VALUE(SUBSTITUTE( INDEX(RESUMO!$J$2:$J$100, MATCH(1, (D11>=RESUMO!$H$2:$H$100)*(D11<=RESUMO!$I$2:$I$100)*(H11>=RESUMO!$K$2:$K$100)*(H11<=RESUMO!$L$2:$L$100), 0)), "R$ ", "")) ))))} -> 85.95 | K11: 0 | L11: =S11/H11 -> 0.050810633 | M11: 1759.12 | N11: 0.16 | O11: {=IF(M11<12.5, 0, IF(M11<29, 6.25, IF(M11<50, 6.5, IF(M11<79, 6.75, VALUE(SUBSTITUTE( INDEX(RESUMO!$J$2:$J$100, MATCH(1, (D11>=RESUMO!$H$2:$H$100)*(D11<=RESUMO!$I$2:$I$100)*(M11>=RESUMO!$K$2:$K$100)*(M11<=RESUMO!$L$2:$L$100), 0)), "R$ ", "")) ))))} -> 85.95 | P11: 0 | Q11: =U11/M11 -> 0.10061917 | R11: =(H11-(H11*I11)-J11-(C11*E11)+K11) -> 1246.7414 | S11: =R11-(C11-F11) -> 78.7514 | T11: =(M11-(M11*N11)-O11-(C11*E11)+P11) -> 1344.9912 | U11: =T11-(C11-F11) -> 177.0012
A12: PHILCO | B12: PHILCO-PMO23E-220V | C12: 459.3 | D12: 13 | E12: 0.04 | F12: 0 | G12: 2 | H12: 549 | I12: 0.11 | J12: {=IF(H12<12.5, H12/2, IF(H12<29, 6.25, IF(H12<50, 6.5, IF(H12<79, 6.75, VALUE(SUBSTITUTE( INDEX(RESUMO!$J$2:$J$100, MATCH(1, (D12>=RESUMO!$H$2:$H$100)*(D12<=RESUMO!$I$2:$I$100)*(H12>=RESUMO!$K$2:$K$100)*(H12<=RESUMO!$L$2:$L$100), 0)), "R$ ", "")) ))))} -> 65.95 | K12: 0 | L12: =S12/H12 -> -0.10020401 | M12: 689 | N12: 0.16 | O12: {=IF(M12<12.5, 0, IF(M12<29, 6.25, IF(M12<50, 6.5, IF(M12<79, 6.75, VALUE(SUBSTITUTE( INDEX(RESUMO!$J$2:$J$100, MATCH(1, (D12>=RESUMO!$H$2:$H$100)*(D12<=RESUMO!$I$2:$I$100)*(M12>=RESUMO!$K$2:$K$100)*(M12<=RESUMO!$L$2:$L$100), 0)), "R$ ", "")) ))))} -> 65.95 | P12: 0 | Q12: =U12/M12 -> 0.050998549 | R12: =(H12-(H12*I12)-J12-(C12*E12)+K12) -> 404.288 | S12: =R12-(C12-F12) -> -55.012 | T12: =(M12-(M12*N12)-O12-(C12*E12)+P12) -> 494.438 | U12: =T12-(C12-F12) -> 35.138
A13: PHILCO | B13: PHILCO-PMO28BB-127V | C13: 487.97 | D13: 13 | E13: 0.04 | F13: 0 | G13: 2 | H13: 685 | I13: 0.11 | J13: {=IF(H13<12.5, H13/2, IF(H13<29, 6.25, IF(H13<50, 6.5, IF(H13<79, 6.75, VALUE(SUBSTITUTE( INDEX(RESUMO!$J$2:$J$100, MATCH(1, (D13>=RESUMO!$H$2:$H$100)*(D13<=RESUMO!$I$2:$I$100)*(H13>=RESUMO!$K$2:$K$100)*(H13<=RESUMO!$L$2:$L$100), 0)), "R$ ", "")) ))))} -> 65.95 | K13: 0 | L13: =S13/H13 -> 0.052863066 | M13: 749 | N13: 0.16 | O13: {=IF(M13<12.5, 0, IF(M13<29, 6.25, IF(M13<50, 6.5, IF(M13<79, 6.75, VALUE(SUBSTITUTE( INDEX(RESUMO!$J$2:$J$100, MATCH(1, (D13>=RESUMO!$H$2:$H$100)*(D13<=RESUMO!$I$2:$I$100)*(M13>=RESUMO!$K$2:$K$100)*(M13<=RESUMO!$L$2:$L$100), 0)), "R$ ", "")) ))))} -> 65.95 | P13: 0 | Q13: =U13/M13 -> 0.074394126 | R13: =(H13-(H13*I13)-J13-(C13*E13)+K13) -> 524.1812 | S13: =R13-(C13-F13) -> 36.2112 | T13: =(M13-(M13*N13)-O13-(C13*E13)+P13) -> 543.6912 | U13: =T13-(C13-F13) -> 55.7212
... A25: PHILCO | B25: PHILCO-PTV100A5DGSPB-BIV | C25: 14845.96 | D25: 30 | E25: 0.04 | F25: 630.27 | G25: 0 | H25: 17690.2 | I25: 0.11 | J25: {=IF(H25<12.5, H25/2, IF(H25<29, 6.25, IF(H25<50, 6.5, IF(H25<79, 6.75, VALUE(SUBSTITUTE( INDEX(RESUMO!$J$2:$J$100, MATCH(1, (D25>=RESUMO!$H$2:$H$100)*(D25<=RESUMO!$I$2:$I$100)*(H25>=RESUMO!$K$2:$K$100)*(H25<=RESUMO!$L$2:$L$100), 0)), "R$ ", "")) ))))} -> 98.95 | K25: 229.98 | L25: =S25/H25 -> 0.060246894 | M25: 19133.06 | N25: 0.16 | O25: {=IF(M25<12.5, 0, IF(M25<29, 6.25, IF(M25<50, 6.5, IF(M25<79, 6.75, VALUE(SUBSTITUTE( INDEX(RESUMO!$J$2:$J$100, MATCH(1, (D25>=RESUMO!$H$2:$H$100)*(D25<=RESUMO!$I$2:$I$100)*(M25>=RESUMO!$K$2:$K$100)*(M25<=RESUMO!$L$2:$L$100), 0)), "R$ ", "")) ))))} -> 98.95 | P25: 230.69 | Q25: =U25/M25 -> 0.072857243 | R25: =(H25-(H25*I25)-J25-(C25*E25)+K25) -> 15281.47 | S25: =R25-(C25-F25) -> 1065.7796 | T25: =(M25-(M25*N25)-O25-(C25*E25)+P25) -> 15609.672 | U25: =T25-(C25-F25) -> 1393.982
A26: BRITANIA | B26: BRITANIA-BTV43VA4REGB-BIV | C26: 1238.87 | D26: 13 | E26: 0.04 | F26: 0 | G26: 0 | H26: 1661.55 | I26: 0.11 | K26: 0 | L26: =S26/H26 -> #VALUE! | M26: 1781.25 | N26: 0.16 | O26: {=IF(M26<12.5, 0, IF(M26<29, 6.25, IF(M26<50, 6.5, IF(M26<79, 6.75, VALUE(SUBSTITUTE( INDEX(RESUMO!$J$2:$J$100, MATCH(1, (D26>=RESUMO!$H$2:$H$100)*(D26<=RESUMO!$I$2:$I$100)*(M26>=RESUMO!$K$2:$K$100)*(M26<=RESUMO!$L$2:$L$100), 0)), "R$ ", "")) ))))} -> 65.95 | P26: 0 | Q26: =U26/M26 -> 0.079649235 | R26: =(H26-(H26*I26)-J26-(C26*E26)+K26) -> #VALUE! | S26: =R26-(C26-F26) -> #VALUE! | T26: =(M26-(M26*N26)-O26-(C26*E26)+P26) -> 1380.7452 | U26: =T26-(C26-F26) -> 141.8752
A27: BRITANIA | B27: BRITANIA-BTV50VA4REGB-BIV | C27: 1771.27 | D27: 23 | E27: 0.04 | F27: 0 | G27: 0 | H27: 2067.3 | I27: 0.11 | J27: {=IF(H27<12.5, H27/2, IF(H27<29, 6.25, IF(H27<50, 6.5, IF(H27<79, 6.75, VALUE(SUBSTITUTE( INDEX(RESUMO!$J$2:$J$100, MATCH(1, (D27>=RESUMO!$H$2:$H$100)*(D27<=RESUMO!$I$2:$I$100)*(H27>=RESUMO!$K$2:$K$100)*(H27<=RESUMO!$L$2:$L$100), 0)), "R$ ", "")) ))))} -> 85.95 | K27: 0 | L27: =S27/H27 -> -0.042651671 | M27: 2493.14 | N27: 0.16 | O27: {=IF(M27<12.5, 0, IF(M27<29, 6.25, IF(M27<50, 6.5, IF(M27<79, 6.75, VALUE(SUBSTITUTE( INDEX(RESUMO!$J$2:$J$100, MATCH(1, (D27>=RESUMO!$H$2:$H$100)*(D27<=RESUMO!$I$2:$I$100)*(M27>=RESUMO!$K$2:$K$100)*(M27<=RESUMO!$L$2:$L$100), 0)), "R$ ", "")) ))))} -> 85.95 | P27: 0 | Q27: =U27/M27 -> 0.066649607 | R27: =(H27-(H27*I27)-J27-(C27*E27)+K27) -> 1683.0962 | S27: =R27-(C27-F27) -> -88.1738 | T27: =(M27-(M27*N27)-O27-(C27*E27)+P27) -> 1937.4368 | U27: =T27-(C27-F27) -> 166.1668
A28: PHILCO | B28: PHILCO-PTV42G6FR2CPF-42 | C28: 1238.87 | D28: 13 | E28: 0.04 | F28: 0 | G28: 0 | H28: 1443.91 | I28: 0.11 | J28: {=IF(H28<12.5, H28/2, IF(H28<29, 6.25, IF(H28<50, 6.5, IF(H28<79, 6.75, VALUE(SUBSTITUTE( INDEX(RESUMO!$J$2:$J$100, MATCH(1, (D28>=RESUMO!$H$2:$H$100)*(D28<=RESUMO!$I$2:$I$100)*(H28>=RESUMO!$K$2:$K$100)*(H28<=RESUMO!$L$2:$L$100), 0)), "R$ ", "")) ))))} -> 65.95 | K28: 0 | L28: =S28/H28 -> -0.047991149 | M28: 1642.5 | N28: 0.16 | O28: {=IF(M28<12.5, 0, IF(M28<29, 6.25, IF(M28<50, 6.5, IF(M28<79, 6.75, VALUE(SUBSTITUTE( INDEX(RESUMO!$J$2:$J$100, MATCH(1, (D28>=RESUMO!$H$2:$H$100)*(D28<=RESUMO!$I$2:$I$100)*(M28>=RESUMO!$K$2:$K$100)*(M28<=RESUMO!$L$2:$L$100), 0)), "R$ ", "")) ))))} -> 65.95 | P28: 0 | Q28: =U28/M28 -> 0.015418691 | R28: =(H28-(H28*I28)-J28-(C28*E28)+K28) -> 1169.5751 | S28: =R28-(C28-F28) -> -69.2949 | T28: =(M28-(M28*N28)-O28-(C28*E28)+P28) -> 1264.1952 | U28: =T28-(C28-F28) -> 25.3252
A29: PHILCO | B29: PHILCO-PMO33EB-127V | C29: 608.23 | D29: 17 | E29: 0.04 | F29: 0 | G29: 2 | H29: 845.06 | I29: 0.11 | J29: {=IF(H29<12.5, H29/2, IF(H29<29, 6.25, IF(H29<50, 6.5, IF(H29<79, 6.75, VALUE(SUBSTITUTE( INDEX(RESUMO!$J$2:$J$100, MATCH(1, (D29>=RESUMO!$H$2:$H$100)*(D29<=RESUMO!$I$2:$I$100)*(H29>=RESUMO!$K$2:$K$100)*(H29<=RESUMO!$L$2:$L$100), 0)), "R$ ", "")) ))))} -> 73.45 | K29: 0 | L29: =S29/H29 -> 0.054545476 | M29: 899.9 | N29: 0.16 | O29: {=IF(M29<12.5, 0, IF(M29<29, 6.25, IF(M29<50, 6.5, IF(M29<79, 6.75, VALUE(SUBSTITUTE( INDEX(RESUMO!$J$2:$J$100, MATCH(1, (D29>=RESUMO!$H$2:$H$100)*(D29<=RESUMO!$I$2:$I$100)*(M29>=RESUMO!$K$2:$K$100)*(M29<=RESUMO!$L$2:$L$100), 0)), "R$ ", "")) ))))} -> 73.45 | P29: 0 | Q29: =U29/M29 -> 0.055458162 | R29: =(H29-(H29*I29)-J29-(C29*E29)+K29) -> 654.3242 | S29: =R29-(C29-F29) -> 46.0942 | T29: =(M29-(M29*N29)-O29-(C29*E29)+P29) -> 658.1368 | U29: =T29-(C29-F29) -> 49.9068
A30: PHILCO | B30: PHILCO-PMO33IP-127V | C30: 613.74 | D30: 17 | E30: 0.04 | F30: 0 | G30: 2 | H30: 799.9 | I30: 0.11 | J30: {=IF(H30<12.5, H30/2, IF(H30<29, 6.25, IF(H30<50, 6.5, IF(H30<79, 6.75, VALUE(SUBSTITUTE( INDEX(RESUMO!$J$2:$J$100, MATCH(1, (D30>=RESUMO!$H$2:$H$100)*(D30<=RESUMO!$I$2:$I$100)*(H30>=RESUMO!$K$2:$K$100)*(H30<=RESUMO!$L$2:$L$100), 0)), "R$ ", "")) ))))} -> 73.45 | K30: 0 | L30: =S30/H30 -> 0.00021427678 | M30: 849 | N30: 0.16 | O30: {=IF(M30<12.5, 0, IF(M30<29, 6.25, IF(M30<50, 6.5, IF(M30<79, 6.75, VALUE(SUBSTITUTE( INDEX(RESUMO!$J$2:$J$100, MATCH(1, (D30>=RESUMO!$H$2:$H$100)*(D30<=RESUMO!$I$2:$I$100)*(M30>=RESUMO!$K$2:$K$100)*(M30<=RESUMO!$L$2:$L$100), 0)), "R$ ", "")) ))))} -> 73.45 | P30: 0 | Q30: =U30/M30 -> 0.0016730271 | R30: =(H30-(H30*I30)-J30-(C30*E30)+K30) -> 613.9114 | S30: =R30-(C30-F30) -> 0.1714 | T30: =(M30-(M30*N30)-O30-(C30*E30)+P30) -> 615.1604 | U30: =T30-(C30-F30) -> 1.4204
A31: PHILCO | B31: PHILCO-PTV40M9GACGB-BIV | C31: 1197.91 | D31: 13 | E31: 0.04 | F31: 0 | G31: 0 | H31: 1399 | I31: 0.11 | J31: {=IF(H31<12.5, H31/2, IF(H31<29, 6.25, IF(H31<50, 6.5, IF(H31<79, 6.75, VALUE(SUBSTITUTE( INDEX(RESUMO!$J$2:$J$100, MATCH(1, (D31>=RESUMO!$H$2:$H$100)*(D31<=RESUMO!$I$2:$I$100)*(H31>=RESUMO!$K$2:$K$100)*(H31<=RESUMO!$L$2:$L$100), 0)), "R$ ", "")) ))))} -> 65.95 | K31: 0 | L31: =S31/H31 -> -0.047652895 | M31: 1614.15 | N31: 0.16 | O31: {=IF(M31<12.5, 0, IF(M31<29, 6.25, IF(M31<50, 6.5, IF(M31<79, 6.75, VALUE(SUBSTITUTE( INDEX(RESUMO!$J$2:$J$100, MATCH(1, (D31>=RESUMO!$H$2:$H$100)*(D31<=RESUMO!$I$2:$I$100)*(M31>=RESUMO!$K$2:$K$100)*(M31<=RESUMO!$L$2:$L$100), 0)), "R$ ", "")) ))))} -> 65.95 | P31: 0 | Q31: =U31/M31 -> 0.027326828 | R31: =(H31-(H31*I31)-J31-(C31*E31)+K31) -> 1131.2436 | S31: =R31-(C31-F31) -> -66.6664 | T31: =(M31-(M31*N31)-O31-(C31*E31)+P31) -> 1242.0196 | U31: =T31-(C31-F31) -> 44.1096
A32: PHILCO | B32: PHILCO-PMO38B-220V | C32: 549.54 | D32: 17 | E32: 0.04 | F32: 0 | G32: 2 | H32: 729 | I32: 0.11 | J32: {=IF(H32<12.5, H32/2, IF(H32<29, 6.25, IF(H32<50, 6.5, IF(H32<79, 6.75, VALUE(SUBSTITUTE( INDEX(RESUMO!$J$2:$J$100, MATCH(1, (D32>=RESUMO!$H$2:$H$100)*(D32<=RESUMO!$I$2:$I$100)*(H32>=RESUMO!$K$2:$K$100)*(H32<=RESUMO!$L$2:$L$100), 0)), "R$ ", "")) ))))} -> 73.45 | K32: 0 | L32: =S32/H32 -> 0.0052652949 | M32: 775 | N32: 0.16 | O32: {=IF(M32<12.5, 0, IF(M32<29, 6.25, IF(M32<50, 6.5, IF(M32<79, 6.75, VALUE(SUBSTITUTE( INDEX(RESUMO!$J$2:$J$100, MATCH(1, (D32>=RESUMO!$H$2:$H$100)*(D32<=RESUMO!$I$2:$I$100)*(M32>=RESUMO!$K$2:$K$100)*(M32<=RESUMO!$L$2:$L$100), 0)), "R$ ", "")) ))))} -> 73.45 | P32: 0 | Q32: =U32/M32 -> 0.0077785806 | R32: =(H32-(H32*I32)-J32-(C32*E32)+K32) -> 553.3784 | S32: =R32-(C32-F32) -> 3.8384 | T32: =(M32-(M32*N32)-O32-(C32*E32)+P32) -> 555.5684 | U32: =T32-(C32-F32) -> 6.0284
A33: PHILCO | B33: PHILCO-PMO23B-220V | C33: 439.02 | D33: 13 | E33: 0.04 | F33: 0 | G33: 2 | H33: 623.5 | I33: 0.11 | J33: {=IF(H33<12.5, H33/2, IF(H33<29, 6.25, IF(H33<50, 6.5, IF(H33<79, 6.75, VALUE(SUBSTITUTE( INDEX(RESUMO!$J$2:$J$100, MATCH(1, (D33>=RESUMO!$H$2:$H$100)*(D33<=RESUMO!$I$2:$I$100)*(H33>=RESUMO!$K$2:$K$100)*(H33<=RESUMO!$L$2:$L$100), 0)), "R$ ", "")) ))))} -> 65.95 | K33: 0 | L33: =S33/H33 -> 0.051939374 | M33: 665 | N33: 0.16 | O33: {=IF(M33<12.5, 0, IF(M33<29, 6.25, IF(M33<50, 6.5, IF(M33<79, 6.75, VALUE(SUBSTITUTE( INDEX(RESUMO!$J$2:$J$100, MATCH(1, (D33>=RESUMO!$H$2:$H$100)*(D33<=RESUMO!$I$2:$I$100)*(M33>=RESUMO!$K$2:$K$100)*(M33<=RESUMO!$L$2:$L$100), 0)), "R$ ", "")) ))))} -> 65.95 | P33: 0 | Q33: =U33/M33 -> 0.054239398 | R33: =(H33-(H33*I33)-J33-(C33*E33)+K33) -> 471.4042 | S33: =R33-(C33-F33) -> 32.3842 | T33: =(M33-(M33*N33)-O33-(C33*E33)+P33) -> 475.0892 | U33: =T33-(C33-F33) -> 36.0692
A34: BRITANIA | B34: BRITANIA-BMO23-220V | C34: 439.02 | D34: 17 | E34: 0.04 | F34: 0 | G34: 2 | H34: 549.9 | I34: 0.11 | J34: {=IF(H34<12.5, H34/2, IF(H34<29, 6.25, IF(H34<50, 6.5, IF(H34<79, 6.75, VALUE(SUBSTITUTE( INDEX(RESUMO!$J$2:$J$100, MATCH(1, (D34>=RESUMO!$H$2:$H$100)*(D34<=RESUMO!$I$2:$I$100)*(H34>=RESUMO!$K$2:$K$100)*(H34<=RESUMO!$L$2:$L$100), 0)), "R$ ", "")) ))))} -> 73.45 | K34: 0 | L34: =S34/H34 -> -0.073867612 | M34: 599 | N34: 0.16 | O34: {=IF(M34<12.5, 0, IF(M34<29, 6.25, IF(M34<50, 6.5, IF(M34<79, 6.75, VALUE(SUBSTITUTE( INDEX(RESUMO!$J$2:$J$100, MATCH(1, (D34>=RESUMO!$H$2:$H$100)*(D34<=RESUMO!$I$2:$I$100)*(M34>=RESUMO!$K$2:$K$100)*(M34<=RESUMO!$L$2:$L$100), 0)), "R$ ", "")) ))))} -> 73.45 | P34: 0 | Q34: =U34/M34 -> -0.044859432 | R34: =(H34-(H34*I34)-J34-(C34*E34)+K34) -> 398.4002 | S34: =R34-(C34-F34) -> -40.6198 | T34: =(M34-(M34*N34)-O34-(C34*E34)+P34) -> 412.1492 | U34: =T34-(C34-F34) -> -26.8708
A35: PHILCO | B35: PHILCO-PDR60P-220V | C35: 266.68 | D35: 70 | E35: 0.04 | F35: 0 | G35: 0 | H35: 483 | I35: 0.11 | J35: {=IF(H35<12.5, H35/2, IF(H35<29, 6.25, IF(H35<50, 6.5, IF(H35<79, 6.75, VALUE(SUBSTITUTE( INDEX(RESUMO!$J$2:$J$100, MATCH(1, (D35>=RESUMO!$H$2:$H$100)*(D35<=RESUMO!$I$2:$I$100)*(H35>=RESUMO!$K$2:$K$100)*(H35<=RESUMO!$L$2:$L$100), 0)), "R$ ", "")) ))))} -> 120.45 | K35: 0 | L35: =S35/H35 -> 0.066403313 | M35: 529 | N35: 0.16 | O35: {=IF(M35<12.5, 0, IF(M35<29, 6.25, IF(M35<50, 6.5, IF(M35<79, 6.75, VALUE(SUBSTITUTE( INDEX(RESUMO!$J$2:$J$100, MATCH(1, (D35>=RESUMO!$H$2:$H$100)*(D35<=RESUMO!$I$2:$I$100)*(M35>=RESUMO!$K$2:$K$100)*(M35<=RESUMO!$L$2:$L$100), 0)), "R$ ", "")) ))))} -> 120.45 | P35: 0 | Q35: =U35/M35 -> 0.088020416 | R35: =(H35-(H35*I35)-J35-(C35*E35)+K35) -> 298.7528 | S35: =R35-(C35-F35) -> 32.0728 | T35: =(M35-(M35*N35)-O35-(C35*E35)+P35) -> 313.2428 | U35: =T35-(C35-F35) -> 46.5628
A36: PHILCO | B36: PHILCO-PMG01PI-220V | C36: 822.61 | D36: 9 | E36: 0.04 | F36: 0 | G36: 2 | H36: 1015 | I36: 0.11 | J36: {=IF(H36<12.5, H36/2, IF(H36<29, 6.25, IF(H36<50, 6.5, IF(H36<79, 6.75, VALUE(SUBSTITUTE( INDEX(RESUMO!$J$2:$J$100, MATCH(1, (D36>=RESUMO!$H$2:$H$100)*(D36<=RESUMO!$I$2:$I$100)*(H36>=RESUMO!$K$2:$K$100)*(H36<=RESUMO!$L$2:$L$100), 0)), "R$ ", "")) ))))} -> 44.45 | K36: 0 | L36: =S36/H36 -> 0.0033355665 | M36: 1095 | N36: 0.17 | O36: {=IF(M36<12.5, 0, IF(M36<29, 6.25, IF(M36<50, 6.5, IF(M36<79, 6.75, VALUE(SUBSTITUTE( INDEX(RESUMO!$J$2:$J$100, MATCH(1, (D36>=RESUMO!$H$2:$H$100)*(D36<=RESUMO!$I$2:$I$100)*(M36>=RESUMO!$K$2:$K$100)*(M36<=RESUMO!$L$2:$L$100), 0)), "R$ ", "")) ))))} -> 44.45 | P36: 0 | Q36: =U36/M36 -> 0.0081147032 | R36: =(H36-(H36*I36)-J36-(C36*E36)+K36) -> 825.9956 | S36: =R36-(C36-F36) -> 3.3856 | T36: =(M36-(M36*N36)-O36-(C36*E36)+P36) -> 831.4956 | U36: =T36-(C36-F36) -> 8.8856
A37: PHILCO | B37: PHILCO-PCO60G-220V | C37: 591.67 | D37: 70 | E37: 0.04 | F37: 0 | G37: 0 | H37: 897.45 | I37: 0.11 | J37: {=IF(H37<12.5, H37/2, IF(H37<29, 6.25, IF(H37<50, 6.5, IF(H37<79, 6.75, VALUE(SUBSTITUTE( INDEX(RESUMO!$J$2:$J$100, MATCH(1, (D37>=RESUMO!$H$2:$H$100)*(D37<=RESUMO!$I$2:$I$100)*(H37>=RESUMO!$K$2:$K$100)*(H37<=RESUMO!$L$2:$L$100), 0)), "R$ ", "")) ))))} -> 120.45 | K37: 0 | L37: =S37/H37 -> 0.070136164 | M37: 1025 | N37: 0.16 | O37: {=IF(M37<12.5, 0, IF(M37<29, 6.25, IF(M37<50, 6.5, IF(M37<79, 6.75, VALUE(SUBSTITUTE( INDEX(RESUMO!$J$2:$J$100, MATCH(1, (D37>=RESUMO!$H$2:$H$100)*(D37<=RESUMO!$I$2:$I$100)*(M37>=RESUMO!$K$2:$K$100)*(M37<=RESUMO!$L$2:$L$100), 0)), "R$ ", "")) ))))} -> 120.45 | P37: 0 | Q37: =U37/M37 -> 0.12215922 | R37: =(H37-(H37*I37)-J37-(C37*E37)+K37) -> 654.6137 | S37: =R37-(C37-F37) -> 62.9437 | T37: =(M37-(M37*N37)-O37-(C37*E37)+P37) -> 716.8832 | U37: =T37-(C37-F37) -> 125.2132
A38: PHILCO | B38: PHILCO-PAD24DZ-BIV | C38: 1327.28 | D38: 40 | E38: 0.04 | F38: 0 | G38: 2 | H38: 1685 | I38: 0.115 | J38: {=IF(H38<12.5, H38/2, IF(H38<29, 6.25, IF(H38<50, 6.5, IF(H38<79, 6.75, VALUE(SUBSTITUTE( INDEX(RESUMO!$J$2:$J$100, MATCH(1, (D38>=RESUMO!$H$2:$H$100)*(D38<=RESUMO!$I$2:$I$100)*(H38>=RESUMO!$K$2:$K$100)*(H38<=RESUMO!$L$2:$L$100), 0)), "R$ ", "")) ))))} -> 101.95 | K38: 0 | L38: =S38/H38 -> 0.0052841543 | M38: 1785 | N38: 0.165 | O38: {=IF(M38<12.5, 0, IF(M38<29, 6.25, IF(M38<50, 6.5, IF(M38<79, 6.75, VALUE(SUBSTITUTE( INDEX(RESUMO!$J$2:$J$100, MATCH(1, (D38>=RESUMO!$H$2:$H$100)*(D38<=RESUMO!$I$2:$I$100)*(M38>=RESUMO!$K$2:$K$100)*(M38<=RESUMO!$L$2:$L$100), 0)), "R$ ", "")) ))))} -> 101.95 | P38: 0 | Q38: =U38/M38 -> 0.0045679552 | R38: =(H38-(H38*I38)-J38-(C38*E38)+K38) -> 1336.1838 | S38: =R38-(C38-F38) -> 8.9038 | T38: =(M38-(M38*N38)-O38-(C38*E38)+P38) -> 1335.4338 | U38: =T38-(C38-F38) -> 8.1538
... A53: MONDIAL | B53: MONDIAL-FR-42-127V | C53: 298.9 | D53: 17 | E53: 0.04 | F53: 0 | G53: 2 | H53: 432 | I53: 0.11 | J53: {=IF(H53<12.5, H53/2, IF(H53<29, 6.25, IF(H53<50, 6.5, IF(H53<79, 6.75, VALUE(SUBSTITUTE( INDEX(RESUMO!$J$2:$J$100, MATCH(1, (D53>=RESUMO!$H$2:$H$100)*(D53<=RESUMO!$I$2:$I$100)*(H53>=RESUMO!$K$2:$K$100)*(H53<=RESUMO!$L$2:$L$100), 0)), "R$ ", "")) ))))} -> 73.45 | K53: 0 | L53: =S53/H53 -> 0.00040277778 | M53: 459 | N53: 0.16 | O53: {=IF(M53<12.5, 0, IF(M53<29, 6.25, IF(M53<50, 6.5, IF(M53<79, 6.75, VALUE(SUBSTITUTE( INDEX(RESUMO!$J$2:$J$100, MATCH(1, (D53>=RESUMO!$H$2:$H$100)*(D53<=RESUMO!$I$2:$I$100)*(M53>=RESUMO!$K$2:$K$100)*(M53<=RESUMO!$L$2:$L$100), 0)), "R$ ", "")) ))))} -> 73.45 | P53: 0 | Q53: =U53/M53 -> 0.0027320261 | R53: =(H53-(H53*I53)-J53-(C53*E53)+K53) -> 299.074 | S53: =R53-(C53-F53) -> 0.174 | T53: =(M53-(M53*N53)-O53-(C53*E53)+P53) -> 300.154 | U53: =T53-(C53-F53) -> 1.254
A54: MONDIAL | B54: MONDIAL-ES-14-127V | C54: 106.99 | D54: 1 | E54: 0.04 | F54: 0 | G54: 2 | H54: 145.4 | I54: 0.12 | J54: {=IF(H54<12.5, H54/2, IF(H54<29, 6.25, IF(H54<50, 6.5, IF(H54<79, 6.75, VALUE(SUBSTITUTE( INDEX(RESUMO!$J$2:$J$100, MATCH(1, (D54>=RESUMO!$H$2:$H$100)*(D54<=RESUMO!$I$2:$I$100)*(H54>=RESUMO!$K$2:$K$100)*(H54<=RESUMO!$L$2:$L$100), 0)), "R$ ", "")) ))))} -> 17.95 | K54: 1.86 | L54: =S54/H54 -> 0.0040742779 | O54: {=IF(M54<12.5, 0, IF(M54<29, 6.25, IF(M54<50, 6.5, IF(M54<79, 6.75, VALUE(SUBSTITUTE( INDEX(RESUMO!$J$2:$J$100, MATCH(1, (D54>=RESUMO!$H$2:$H$100)*(D54<=RESUMO!$I$2:$I$100)*(M54>=RESUMO!$K$2:$K$100)*(M54<=RESUMO!$L$2:$L$100), 0)), "R$ ", "")) ))))} -> 0 | Q54: =U54/M54 -> #DIV/0! | R54: =(H54-(H54*I54)-J54-(C54*E54)+K54) -> 107.5824 | S54: =R54-(C54-F54) -> 0.5924 | T54: =(M54-(M54*N54)-O54-(C54*E54)+P54) -> -4.2796 | U54: =T54-(C54-F54) -> -111.2696
A55: THUNDEROBOT | B55: THUNDEROBOT-MG301 | C55: 139.2 | D55: 0.3 | E55: 0.04 | F55: 0 | G55: 2 | H55: 165 | I55: 0.13 | J55: {=IF(H55<12.5, H55/2, IF(H55<29, 6.25, IF(H55<50, 6.5, IF(H55<79, 6.75, VALUE(SUBSTITUTE( INDEX(RESUMO!$J$2:$J$100, MATCH(1, (D55>=RESUMO!$H$2:$H$100)*(D55<=RESUMO!$I$2:$I$100)*(H55>=RESUMO!$K$2:$K$100)*(H55<=RESUMO!$L$2:$L$100), 0)), "R$ ", "")) ))))} -> 17.95 | K55: 0 | L55: =S55/H55 -> -0.1161697 | O55: {=IF(M55<12.5, 0, IF(M55<29, 6.25, IF(M55<50, 6.5, IF(M55<79, 6.75, VALUE(SUBSTITUTE( INDEX(RESUMO!$J$2:$J$100, MATCH(1, (D55>=RESUMO!$H$2:$H$100)*(D55<=RESUMO!$I$2:$I$100)*(M55>=RESUMO!$K$2:$K$100)*(M55<=RESUMO!$L$2:$L$100), 0)), "R$ ", "")) ))))} -> 0 | Q55: =U55/M55 -> #DIV/0! | R55: =(H55-(H55*I55)-J55-(C55*E55)+K55) -> 120.032 | S55: =R55-(C55-F55) -> -19.168 | T55: =(M55-(M55*N55)-O55-(C55*E55)+P55) -> -5.568 | U55: =T55-(C55-F55) -> -144.768
A56: THUNDEROBOT | B56: THUNDEROBOT-H3 | C56: 140.37 | D56: 2 | E56: 0.04 | F56: 0 | G56: 2 | H56: 129.9 | I56: 0.13 | J56: {=IF(H56<12.5, H56/2, IF(H56<29, 6.25, IF(H56<50, 6.5, IF(H56<79, 6.75, VALUE(SUBSTITUTE( INDEX(RESUMO!$J$2:$J$100, MATCH(1, (D56>=RESUMO!$H$2:$H$100)*(D56<=RESUMO!$I$2:$I$100)*(H56>=RESUMO!$K$2:$K$100)*(H56<=RESUMO!$L$2:$L$100), 0)), "R$ ", "")) ))))} -> 18.76 | K56: 0 | L56: =S56/H56 -> -0.39824326 | O56: {=IF(M56<12.5, 0, IF(M56<29, 6.25, IF(M56<50, 6.5, IF(M56<79, 6.75, VALUE(SUBSTITUTE( INDEX(RESUMO!$J$2:$J$100, MATCH(1, (D56>=RESUMO!$H$2:$H$100)*(D56<=RESUMO!$I$2:$I$100)*(M56>=RESUMO!$K$2:$K$100)*(M56<=RESUMO!$L$2:$L$100), 0)), "R$ ", "")) ))))} -> 0 | Q56: =U56/M56 -> #DIV/0! | R56: =(H56-(H56*I56)-J56-(C56*E56)+K56) -> 88.6382 | S56: =R56-(C56-F56) -> -51.7318 | T56: =(M56-(M56*N56)-O56-(C56*E56)+P56) -> -5.6148 | U56: =T56-(C56-F56) -> -145.9848
A57: THUNDEROBOT | B57: THUNDEROBOT-HG503 | C57: 204.75 | D57: 3 | E57: 0.04 | F57: 0 | G57: 2 | H57: 199.9 | I57: 0.13 | J57: {=IF(H57<12.5, H57/2, IF(H57<29, 6.25, IF(H57<50, 6.5, IF(H57<79, 6.75, VALUE(SUBSTITUTE( INDEX(RESUMO!$J$2:$J$100, MATCH(1, (D57>=RESUMO!$H$2:$H$100)*(D57<=RESUMO!$I$2:$I$100)*(H57>=RESUMO!$K$2:$K$100)*(H57<=RESUMO!$L$2:$L$100), 0)), "R$ ", "")) ))))} -> 22.45 | K57: 0 | L57: =S57/H57 -> -0.30753877 | O57: {=IF(M57<12.5, 0, IF(M57<29, 6.25, IF(M57<50, 6.5, IF(M57<79, 6.75, VALUE(SUBSTITUTE( INDEX(RESUMO!$J$2:$J$100, MATCH(1, (D57>=RESUMO!$H$2:$H$100)*(D57<=RESUMO!$I$2:$I$100)*(M57>=RESUMO!$K$2:$K$100)*(M57<=RESUMO!$L$2:$L$100), 0)), "R$ ", "")) ))))} -> 0 | Q57: =U57/M57 -> #DIV/0! | R57: =(H57-(H57*I57)-J57-(C57*E57)+K57) -> 143.273 | S57: =R57-(C57-F57) -> -61.477 | T57: =(M57-(M57*N57)-O57-(C57*E57)+P57) -> -8.19 | U57: =T57-(C57-F57) -> -212.94
A58: PHILCO | B58: PHILCO-PAS1450C-220V | C58: 119.67 | D58: 3 | E58: 0.04 | F58: 0 | G58: 2 | H58: 165 | I58: 0.11 | J58: {=IF(H58<12.5, H58/2, IF(H58<29, 6.25, IF(H58<50, 6.5, IF(H58<79, 6.75, VALUE(SUBSTITUTE( INDEX(RESUMO!$J$2:$J$100, MATCH(1, (D58>=RESUMO!$H$2:$H$100)*(D58<=RESUMO!$I$2:$I$100)*(H58>=RESUMO!$K$2:$K$100)*(H58<=RESUMO!$L$2:$L$100), 0)), "R$ ", "")) ))))} -> 22.45 | K58: 0 | L58: =S58/H58 -> -0.00034424242 | M58: 175 | N58: 0.16 | O58: {=IF(M58<12.5, 0, IF(M58<29, 6.25, IF(M58<50, 6.5, IF(M58<79, 6.75, VALUE(SUBSTITUTE( INDEX(RESUMO!$J$2:$J$100, MATCH(1, (D58>=RESUMO!$H$2:$H$100)*(D58<=RESUMO!$I$2:$I$100)*(M58>=RESUMO!$K$2:$K$100)*(M58<=RESUMO!$L$2:$L$100), 0)), "R$ ", "")) ))))} -> 22.45 | P58: 0 | Q58: =U58/M58 -> 0.00053257143 | R58: =(H58-(H58*I58)-J58-(C58*E58)+K58) -> 119.6132 | S58: =R58-(C58-F58) -> -0.0568 | T58: =(M58-(M58*N58)-O58-(C58*E58)+P58) -> 119.7632 | U58: =T58-(C58-F58) -> 0.0932
A59: BRITANIA | B59: BRITANIA-BAS1500V-127V | C59: 130.51 | D59: 3 | E59: 0.04 | F59: 0 | G59: 0 | H59: 191.4 | I59: 0.11 | J59: {=IF(H59<12.5, H59/2, IF(H59<29, 6.25, IF(H59<50, 6.5, IF(H59<79, 6.75, VALUE(SUBSTITUTE( INDEX(RESUMO!$J$2:$J$100, MATCH(1, (D59>=RESUMO!$H$2:$H$100)*(D59<=RESUMO!$I$2:$I$100)*(H59>=RESUMO!$K$2:$K$100)*(H59<=RESUMO!$L$2:$L$100), 0)), "R$ ", "")) ))))} -> 22.45 | K59: 0 | L59: =S59/H59 -> 0.063561129 | M59: 204.45 | N59: 0.16 | O59: {=IF(M59<12.5, 0, IF(M59<29, 6.25, IF(M59<50, 6.5, IF(M59<79, 6.75, VALUE(SUBSTITUTE( INDEX(RESUMO!$J$2:$J$100, MATCH(1, (D59>=RESUMO!$H$2:$H$100)*(D59<=RESUMO!$I$2:$I$100)*(M59>=RESUMO!$K$2:$K$100)*(M59<=RESUMO!$L$2:$L$100), 0)), "R$ ", "")) ))))} -> 24.95 | P59: 0 | Q59: =U59/M59 -> 0.054084617 | R59: =(H59-(H59*I59)-J59-(C59*E59)+K59) -> 142.6756 | S59: =R59-(C59-F59) -> 12.1656 | T59: =(M59-(M59*N59)-O59-(C59*E59)+P59) -> 141.5676 | U59: =T59-(C59-F59) -> 11.0576
A60: PHILCO | B60: PHILCO-PAS1600P-220V | C60: 135.64 | D60: 3 | E60: 0.04 | F60: 0 | G60: 2 | H60: 185 | I60: 0.11 | J60: {=IF(H60<12.5, H60/2, IF(H60<29, 6.25, IF(H60<50, 6.5, IF(H60<79, 6.75, VALUE(SUBSTITUTE( INDEX(RESUMO!$J$2:$J$100, MATCH(1, (D60>=RESUMO!$H$2:$H$100)*(D60<=RESUMO!$I$2:$I$100)*(H60>=RESUMO!$K$2:$K$100)*(H60<=RESUMO!$L$2:$L$100), 0)), "R$ ", "")) ))))} -> 22.45 | K60: 0 | L60: =S60/H60 -> 0.0061318919 | M60: 195 | N60: 0.16 | O60: {=IF(M60<12.5, 0, IF(M60<29, 6.25, IF(M60<50, 6.5, IF(M60<79, 6.75, VALUE(SUBSTITUTE( INDEX(RESUMO!$J$2:$J$100, MATCH(1, (D60>=RESUMO!$H$2:$H$100)*(D60<=RESUMO!$I$2:$I$100)*(M60>=RESUMO!$K$2:$K$100)*(M60<=RESUMO!$L$2:$L$100), 0)), "R$ ", "")) ))))} -> 22.45 | P60: 0 | Q60: =U60/M60 -> 0.0014584615 | R60: =(H60-(H60*I60)-J60-(C60*E60)+K60) -> 136.7744 | S60: =R60-(C60-F60) -> 1.1344 | T60: =(M60-(M60*N60)-O60-(C60*E60)+P60) -> 135.9244 | U60: =T60-(C60-F60) -> 0.2844
A61: PHILCO | B61: PHILCO-PAS1600P-127V | C61: 135.64 | D61: 3 | E61: 0.04 | F61: 0 | G61: 2 | H61: 185 | I61: 0.11 | J61: {=IF(H61<12.5, H61/2, IF(H61<29, 6.25, IF(H61<50, 6.5, IF(H61<79, 6.75, VALUE(SUBSTITUTE( INDEX(RESUMO!$J$2:$J$100, MATCH(1, (D61>=RESUMO!$H$2:$H$100)*(D61<=RESUMO!$I$2:$I$100)*(H61>=RESUMO!$K$2:$K$100)*(H61<=RESUMO!$L$2:$L$100), 0)), "R$ ", "")) ))))} -> 22.45 | K61: 0 | L61: =S61/H61 -> 0.0061318919 | M61: 195 | N61: 0.16 | O61: {=IF(M61<12.5, 0, IF(M61<29, 6.25, IF(M61<50, 6.5, IF(M61<79, 6.75, VALUE(SUBSTITUTE( INDEX(RESUMO!$J$2:$J$100, MATCH(1, (D61>=RESUMO!$H$2:$H$100)*(D61<=RESUMO!$I$2:$I$100)*(M61>=RESUMO!$K$2:$K$100)*(M61<=RESUMO!$L$2:$L$100), 0)), "R$ ", "")) ))))} -> 22.45 | P61: 0 | Q61: =U61/M61 -> 0.0014584615 | R61: =(H61-(H61*I61)-J61-(C61*E61)+K61) -> 136.7744 | S61: =R61-(C61-F61) -> 1.1344 | T61: =(M61-(M61*N61)-O61-(C61*E61)+P61) -> 135.9244 | U61: =T61-(C61-F61) -> 0.2844
A62: PHILCO | B62: PHILCO-PLQ1300-VM-127V | C62: 129 | D62: 4 | E62: 0.04 | F62: 0 | G62: 2 | H62: 179 | I62: 0.11 | J62: {=IF(H62<12.5, H62/2, IF(H62<29, 6.25, IF(H62<50, 6.5, IF(H62<79, 6.75, VALUE(SUBSTITUTE( INDEX(RESUMO!$J$2:$J$100, MATCH(1, (D62>=RESUMO!$H$2:$H$100)*(D62<=RESUMO!$I$2:$I$100)*(H62>=RESUMO!$K$2:$K$100)*(H62<=RESUMO!$L$2:$L$100), 0)), "R$ ", "")) ))))} -> 24.25 | K62: 0 | L62: =S62/H62 -> 0.005027933 | M62: 189.9 | N62: 0.16 | O62: {=IF(M62<12.5, 0, IF(M62<29, 6.25, IF(M62<50, 6.5, IF(M62<79, 6.75, VALUE(SUBSTITUTE( INDEX(RESUMO!$J$2:$J$100, MATCH(1, (D62>=RESUMO!$H$2:$H$100)*(D62<=RESUMO!$I$2:$I$100)*(M62>=RESUMO!$K$2:$K$100)*(M62<=RESUMO!$L$2:$L$100), 0)), "R$ ", "")) ))))} -> 24.25 | P62: 0 | Q62: =U62/M62 -> 0.005824118 | R62: =(H62-(H62*I62)-J62-(C62*E62)+K62) -> 129.9 | S62: =R62-(C62-F62) -> 0.9 | T62: =(M62-(M62*N62)-O62-(C62*E62)+P62) -> 130.106 | U62: =T62-(C62-F62) -> 1.106
A63: MONDIAL | B63: MONDIAL-P20-RE-PT-BIV | C63: 91.99 | D63: 0.5 | E63: 0.04 | F63: 0 | G63: 2 | H63: 122.9 | I63: 0.12 | J63: {=IF(H63<12.5, H63/2, IF(H63<29, 6.25, IF(H63<50, 6.5, IF(H63<79, 6.75, VALUE(SUBSTITUTE( INDEX(RESUMO!$J$2:$J$100, MATCH(1, (D63>=RESUMO!$H$2:$H$100)*(D63<=RESUMO!$I$2:$I$100)*(H63>=RESUMO!$K$2:$K$100)*(H63<=RESUMO!$L$2:$L$100), 0)), "R$ ", "")) ))))} -> 17.16 | K63: 0 | L63: =S63/H63 -> -0.038060212 | M63: 154 | N63: 0.17 | O63: {=IF(M63<12.5, 0, IF(M63<29, 6.25, IF(M63<50, 6.5, IF(M63<79, 6.75, VALUE(SUBSTITUTE( INDEX(RESUMO!$J$2:$J$100, MATCH(1, (D63>=RESUMO!$H$2:$H$100)*(D63<=RESUMO!$I$2:$I$100)*(M63>=RESUMO!$K$2:$K$100)*(M63<=RESUMO!$L$2:$L$100), 0)), "R$ ", "")) ))))} -> 19.3 | P63: 0 | Q63: =U63/M63 -> 0.083444156 | R63: =(H63-(H63*I63)-J63-(C63*E63)+K63) -> 87.3124 | S63: =R63-(C63-F63) -> -4.6776 | T63: =(M63-(M63*N63)-O63-(C63*E63)+P63) -> 104.8404 | U63: =T63-(C63-F63) -> 12.8504
A64: PHILCO | B64: PHILCO-CROME-INOX-127V | C64: 137 | D64: 4 | E64: 0.04 | F64: 0 | G64: 2 | H64: 189 | I64: 0.11 | J64: {=IF(H64<12.5, H64/2, IF(H64<29, 6.25, IF(H64<50, 6.5, IF(H64<79, 6.75, VALUE(SUBSTITUTE( INDEX(RESUMO!$J$2:$J$100, MATCH(1, (D64>=RESUMO!$H$2:$H$100)*(D64<=RESUMO!$I$2:$I$100)*(H64>=RESUMO!$K$2:$K$100)*(H64<=RESUMO!$L$2:$L$100), 0)), "R$ ", "")) ))))} -> 24.25 | K64: 0 | L64: =S64/H64 -> 0.0078306878 | M64: 199 | N64: 0.16 | O64: {=IF(M64<12.5, 0, IF(M64<29, 6.25, IF(M64<50, 6.5, IF(M64<79, 6.75, VALUE(SUBSTITUTE( INDEX(RESUMO!$J$2:$J$100, MATCH(1, (D64>=RESUMO!$H$2:$H$100)*(D64<=RESUMO!$I$2:$I$100)*(M64>=RESUMO!$K$2:$K$100)*(M64<=RESUMO!$L$2:$L$100), 0)), "R$ ", "")) ))))} -> 24.25 | P64: 0 | Q64: =U64/M64 -> 0.002160804 | R64: =(H64-(H64*I64)-J64-(C64*E64)+K64) -> 138.48 | S64: =R64-(C64-F64) -> 1.48 | T64: =(M64-(M64*N64)-O64-(C64*E64)+P64) -> 137.43 | U64: =T64-(C64-F64) -> 0.43
A65: PHILCO | B65: PHILCO-PARIS-POWER-PT-127V | C65: 99 | D65: 4 | E65: 0.04 | F65: 0 | G65: 2 | H65: 142 | I65: 0.11 | J65: {=IF(H65<12.5, H65/2, IF(H65<29, 6.25, IF(H65<50, 6.5, IF(H65<79, 6.75, VALUE(SUBSTITUTE( INDEX(RESUMO!$J$2:$J$100, MATCH(1, (D65>=RESUMO!$H$2:$H$100)*(D65<=RESUMO!$I$2:$I$100)*(H65>=RESUMO!$K$2:$K$100)*(H65<=RESUMO!$L$2:$L$100), 0)), "R$ ", "")) ))))} -> 21.56 | K65: 0 | L65: =S65/H65 -> 0.013098592 | M65: 155 | N65: 0.16 | O65: {=IF(M65<12.5, 0, IF(M65<29, 6.25, IF(M65<50, 6.5, IF(M65<79, 6.75, VALUE(SUBSTITUTE( INDEX(RESUMO!$J$2:$J$100, MATCH(1, (D65>=RESUMO!$H$2:$H$100)*(D65<=RESUMO!$I$2:$I$100)*(M65>=RESUMO!$K$2:$K$100)*(M65<=RESUMO!$L$2:$L$100), 0)), "R$ ", "")) ))))} -> 24.25 | P65: 0 | Q65: =U65/M65 -> 0.019290323 | R65: =(H65-(H65*I65)-J65-(C65*E65)+K65) -> 100.86 | S65: =R65-(C65-F65) -> 1.86 | T65: =(M65-(M65*N65)-O65-(C65*E65)+P65) -> 101.99 | U65: =T65-(C65-F65) -> 2.99
A66: PHILCO | B66: PHILCO-PMO34EB-220V | C66: 579.26 | D66: 17 | E66: 0.04 | F66: 0 | G66: 2 | H66: 765 | I66: 0.11 | J66: {=IF(H66<12.5, H66/2, IF(H66<29, 6.25, IF(H66<50, 6.5, IF(H66<79, 6.75, VALUE(SUBSTITUTE( INDEX(RESUMO!$J$2:$J$100, MATCH(1, (D66>=RESUMO!$H$2:$H$100)*(D66<=RESUMO!$I$2:$I$100)*(H66>=RESUMO!$K$2:$K$100)*(H66<=RESUMO!$L$2:$L$100), 0)), "R$ ", "")) ))))} -> 73.45 | K66: 0 | L66: =S66/H66 -> 0.0064962092 | M66: 810 | N66: 0.16 | O66: {=IF(M66<12.5, 0, IF(M66<29, 6.25, IF(M66<50, 6.5, IF(M66<79, 6.75, VALUE(SUBSTITUTE( INDEX(RESUMO!$J$2:$J$100, MATCH(1, (D66>=RESUMO!$H$2:$H$100)*(D66<=RESUMO!$I$2:$I$100)*(M66>=RESUMO!$K$2:$K$100)*(M66<=RESUMO!$L$2:$L$100), 0)), "R$ ", "")) ))))} -> 73.45 | P66: 0 | Q66: =U66/M66 -> 0.0055797531 | R66: =(H66-(H66*I66)-J66-(C66*E66)+K66) -> 584.2296 | S66: =R66-(C66-F66) -> 4.9696 | T66: =(M66-(M66*N66)-O66-(C66*E66)+P66) -> 583.7796 | U66: =T66-(C66-F66) -> 4.5196
A67: PHILCO | B67: PHILCO-PMO28B-127V | C67: 487.97 | D67: 13 | E67: 0.04 | F67: 0 | G67: 2 | H67: 649 | I67: 0.11 | J67: {=IF(H67<12.5, H67/2, IF(H67<29, 6.25, IF(H67<50, 6.5, IF(H67<79, 6.75, VALUE(SUBSTITUTE( INDEX(RESUMO!$J$2:$J$100, MATCH(1, (D67>=RESUMO!$H$2:$H$100)*(D67<=RESUMO!$I$2:$I$100)*(H67>=RESUMO!$K$2:$K$100)*(H67<=RESUMO!$L$2:$L$100), 0)), "R$ ", "")) ))))} -> 65.95 | K67: 0 | L67: =S67/H67 -> 0.0064271186 | M67: 689 | N67: 0.16 | O67: {=IF(M67<12.5, 0, IF(M67<29, 6.25, IF(M67<50, 6.5, IF(M67<79, 6.75, VALUE(SUBSTITUTE( INDEX(RESUMO!$J$2:$J$100, MATCH(1, (D67>=RESUMO!$H$2:$H$100)*(D67<=RESUMO!$I$2:$I$100)*(M67>=RESUMO!$K$2:$K$100)*(M67<=RESUMO!$L$2:$L$100), 0)), "R$ ", "")) ))))} -> 65.95 | P67: 0 | Q67: =U67/M67 -> 0.0077230769 | R67: =(H67-(H67*I67)-J67-(C67*E67)+K67) -> 492.1412 | S67: =R67-(C67-F67) -> 4.1712 | T67: =(M67-(M67*N67)-O67-(C67*E67)+P67) -> 493.2912 | U67: =T67-(C67-F67) -> 5.3212
A68: BRITANIA | B68: BRITANIA-BFE45PI-220V | C68: 369.79 | D68: 17 | E68: 0.04 | F68: 0 | G68: 2 | H68: 519 | I68: 0.11 | J68: {=IF(H68<12.5, H68/2, IF(H68<29, 6.25, IF(H68<50, 6.5, IF(H68<79, 6.75, VALUE(SUBSTITUTE( INDEX(RESUMO!$J$2:$J$100, MATCH(1, (D68>=RESUMO!$H$2:$H$100)*(D68<=RESUMO!$I$2:$I$100)*(H68>=RESUMO!$K$2:$K$100)*(H68<=RESUMO!$L$2:$L$100), 0)), "R$ ", "")) ))))} -> 73.45 | K68: 0 | L68: =S68/H68 -> 0.0074728324 | M68: 549 | N68: 0.16 | O68: {=IF(M68<12.5, 0, IF(M68<29, 6.25, IF(M68<50, 6.5, IF(M68<79, 6.75, VALUE(SUBSTITUTE( INDEX(RESUMO!$J$2:$J$100, MATCH(1, (D68>=RESUMO!$H$2:$H$100)*(D68<=RESUMO!$I$2:$I$100)*(M68>=RESUMO!$K$2:$K$100)*(M68<=RESUMO!$L$2:$L$100), 0)), "R$ ", "")) ))))} -> 73.45 | P68: 0 | Q68: =U68/M68 -> 0.0056983607 | R68: =(H68-(H68*I68)-J68-(C68*E68)+K68) -> 373.6684 | S68: =R68-(C68-F68) -> 3.8784 | T68: =(M68-(M68*N68)-O68-(C68*E68)+P68) -> 372.9184 | U68: =T68-(C68-F68) -> 3.1284
A69: TAIFF | B69: TAIF-ELEGANCE-BIV | C69: 119.9 | D69: 0.5 | E69: 0.04 | F69: 0 | G69: 2 | H69: 165 | I69: 0.12 | J69: {=IF(H69<12.5, H69/2, IF(H69<29, 6.25, IF(H69<50, 6.5, IF(H69<79, 6.75, VALUE(SUBSTITUTE( INDEX(RESUMO!$J$2:$J$100, MATCH(1, (D69>=RESUMO!$H$2:$H$100)*(D69<=RESUMO!$I$2:$I$100)*(H69>=RESUMO!$K$2:$K$100)*(H69<=RESUMO!$L$2:$L$100), 0)), "R$ ", "")) ))))} -> 19.3 | K69: 0 | L69: =S69/H69 -> 0.0072969697 | M69: 175 | N69: 0.17 | O69: {=IF(M69<12.5, 0, IF(M69<29, 6.25, IF(M69<50, 6.5, IF(M69<79, 6.75, VALUE(SUBSTITUTE( INDEX(RESUMO!$J$2:$J$100, MATCH(1, (D69>=RESUMO!$H$2:$H$100)*(D69<=RESUMO!$I$2:$I$100)*(M69>=RESUMO!$K$2:$K$100)*(M69<=RESUMO!$L$2:$L$100), 0)), "R$ ", "")) ))))} -> 19.3 | P69: 0 | Q69: =U69/M69 -> 0.0071657143 | R69: =(H69-(H69*I69)-J69-(C69*E69)+K69) -> 121.104 | S69: =R69-(C69-F69) -> 1.204 | T69: =(M69-(M69*N69)-O69-(C69*E69)+P69) -> 121.154 | U69: =T69-(C69-F69) -> 1.254
... A74: MONDIAL | B74: MONDIAL-AFN40BFS-127V | C74: 229.9 | D74: 9 | E74: 0.04 | F74: 0 | G74: 2 | H74: 319 | I74: 0.11 | J74: {=IF(H74<12.5, H74/2, IF(H74<29, 6.25, IF(H74<50, 6.5, IF(H74<79, 6.75, VALUE(SUBSTITUTE( INDEX(RESUMO!$J$2:$J$100, MATCH(1, (D74>=RESUMO!$H$2:$H$100)*(D74<=RESUMO!$I$2:$I$100)*(H74>=RESUMO!$K$2:$K$100)*(H74<=RESUMO!$L$2:$L$100), 0)), "R$ ", "")) ))))} -> 44.45 | K74: 0 | L74: =S74/H74 -> 0.0011410658 | M74: 339 | N74: 0.16 | O74: {=IF(M74<12.5, 0, IF(M74<29, 6.25, IF(M74<50, 6.5, IF(M74<79, 6.75, VALUE(SUBSTITUTE( INDEX(RESUMO!$J$2:$J$100, MATCH(1, (D74>=RESUMO!$H$2:$H$100)*(D74<=RESUMO!$I$2:$I$100)*(M74>=RESUMO!$K$2:$K$100)*(M74<=RESUMO!$L$2:$L$100), 0)), "R$ ", "")) ))))} -> 44.45 | P74: 0 | Q74: =U74/M74 -> 0.0035811209 | R74: =(H74-(H74*I74)-J74-(C74*E74)+K74) -> 230.264 | S74: =R74-(C74-F74) -> 0.364 | T74: =(M74-(M74*N74)-O74-(C74*E74)+P74) -> 231.114 | U74: =T74-(C74-F74) -> 1.214
A75: POSITIVO | B75: POSITIVO-T30764G-3-64GB | C75: 419 | D75: 0.5 | E75: 0.04 | F75: 0 | G75: 2 | L75: =S75/H75 -> #DIV/0! | M75: 475 | N75: 0.16 | O75: {=IF(M75<12.5, 0, IF(M75<29, 6.25, IF(M75<50, 6.5, IF(M75<79, 6.75, VALUE(SUBSTITUTE( INDEX(RESUMO!$J$2:$J$100, MATCH(1, (D75>=RESUMO!$H$2:$H$100)*(D75<=RESUMO!$I$2:$I$100)*(M75>=RESUMO!$K$2:$K$100)*(M75<=RESUMO!$L$2:$L$100), 0)), "R$ ", "")) ))))} -> 21.45 | P75: 0 | Q75: =U75/M75 -> -0.12254737 | R75: =(H75-(H75*I75)-J75-(C75*E75)+K75) -> -16.76 | S75: =R75-(C75-F75) -> -435.76 | T75: =(M75-(M75*N75)-O75-(C75*E75)+P75) -> 360.79 | U75: =T75-(C75-F75) -> -58.21
A76: LG | B76: LG-43LR671C0SA-AWZ-BIV | C76: 1399 | D76: 23 | E76: 0.04 | F76: 0 | G76: 0 | H76: 1846.5 | I76: 0.11 | J76: {=IF(H76<12.5, H76/2, IF(H76<29, 6.25, IF(H76<50, 6.5, IF(H76<79, 6.75, VALUE(SUBSTITUTE( INDEX(RESUMO!$J$2:$J$100, MATCH(1, (D76>=RESUMO!$H$2:$H$100)*(D76<=RESUMO!$I$2:$I$100)*(H76>=RESUMO!$K$2:$K$100)*(H76<=RESUMO!$L$2:$L$100), 0)), "R$ ", "")) ))))} -> 85.95 | K76: 0 | L76: =S76/H76 -> 0.055496886 | M76: 1899 | N76: 0.16 | O76: {=IF(M76<12.5, 0, IF(M76<29, 6.25, IF(M76<50, 6.5, IF(M76<79, 6.75, VALUE(SUBSTITUTE( INDEX(RESUMO!$J$2:$J$100, MATCH(1, (D76>=RESUMO!$H$2:$H$100)*(D76<=RESUMO!$I$2:$I$100)*(M76>=RESUMO!$K$2:$K$100)*(M76<=RESUMO!$L$2:$L$100), 0)), "R$ ", "")) ))))} -> 85.95 | P76: 0 | Q76: =U76/M76 -> 0.028567667 | R76: =(H76-(H76*I76)-J76-(C76*E76)+K76) -> 1501.475 | S76: =R76-(C76-F76) -> 102.475 | T76: =(M76-(M76*N76)-O76-(C76*E76)+P76) -> 1453.25 | U76: =T76-(C76-F76) -> 54.25
A77: PHILCO | B77: PHILCO-PTV40M9GR2CGB | C77: 1146.73 | D77: 13 | E77: 0.04 | F77: 0 | G77: 0 | H77: 1512.11 | I77: 0.11 | J77: {=IF(H77<12.5, H77/2, IF(H77<29, 6.25, IF(H77<50, 6.5, IF(H77<79, 6.75, VALUE(SUBSTITUTE( INDEX(RESUMO!$J$2:$J$100, MATCH(1, (D77>=RESUMO!$H$2:$H$100)*(D77<=RESUMO!$I$2:$I$100)*(H77>=RESUMO!$K$2:$K$100)*(H77<=RESUMO!$L$2:$L$100), 0)), "R$ ", "")) ))))} -> 65.95 | K77: 0 | L77: =S77/H77 -> 0.057686742 | M77: 1606 | N77: 0.16 | O77: {=IF(M77<12.5, 0, IF(M77<29, 6.25, IF(M77<50, 6.5, IF(M77<79, 6.75, VALUE(SUBSTITUTE( INDEX(RESUMO!$J$2:$J$100, MATCH(1, (D77>=RESUMO!$H$2:$H$100)*(D77<=RESUMO!$I$2:$I$100)*(M77>=RESUMO!$K$2:$K$100)*(M77<=RESUMO!$L$2:$L$100), 0)), "R$ ", "")) ))))} -> 65.95 | P77: 0 | Q77: =U77/M77 -> 0.056345455 | R77: =(H77-(H77*I77)-J77-(C77*E77)+K77) -> 1233.9587 | S77: =R77-(C77-F77) -> 87.2287 | T77: =(M77-(M77*N77)-O77-(C77*E77)+P77) -> 1237.2208 | U77: =T77-(C77-F77) -> 90.4908
A78: PHILCO | B78: PHILCO-PTV32G7PR2CGB | C78: 849.79 | D78: 9 | E78: 0.04 | F78: 0 | G78: 0 | H78: 999 | I78: 0.11 | J78: {=IF(H78<12.5, H78/2, IF(H78<29, 6.25, IF(H78<50, 6.5, IF(H78<79, 6.75, VALUE(SUBSTITUTE( INDEX(RESUMO!$J$2:$J$100, MATCH(1, (D78>=RESUMO!$H$2:$H$100)*(D78<=RESUMO!$I$2:$I$100)*(H78>=RESUMO!$K$2:$K$100)*(H78<=RESUMO!$L$2:$L$100), 0)), "R$ ", "")) ))))} -> 44.45 | K78: 0 | L78: =S78/H78 -> -0.039160761 | M78: 1055 | N78: 0.16 | O78: {=IF(M78<12.5, 0, IF(M78<29, 6.25, IF(M78<50, 6.5, IF(M78<79, 6.75, VALUE(SUBSTITUTE( INDEX(RESUMO!$J$2:$J$100, MATCH(1, (D78>=RESUMO!$H$2:$H$100)*(D78<=RESUMO!$I$2:$I$100)*(M78>=RESUMO!$K$2:$K$100)*(M78<=RESUMO!$L$2:$L$100), 0)), "R$ ", "")) ))))} -> 44.45 | P78: 0 | Q78: =U78/M78 -> -0.039840379 | R78: =(H78-(H78*I78)-J78-(C78*E78)+K78) -> 810.6684 | S78: =R78-(C78-F78) -> -39.1216 | T78: =(M78-(M78*N78)-O78-(C78*E78)+P78) -> 807.7584 | U78: =T78-(C78-F78) -> -42.0316
A79: POSITIVO | B79: POSITIVO-TAB10-T3010D | C79: 860 | D79: 1 | E79: 0.04 | F79: 0 | G79: 2 | H79: 949 | I79: 0.11 | J79: {=IF(H79<12.5, H79/2, IF(H79<29, 6.25, IF(H79<50, 6.5, IF(H79<79, 6.75, VALUE(SUBSTITUTE( INDEX(RESUMO!$J$2:$J$100, MATCH(1, (D79>=RESUMO!$H$2:$H$100)*(D79<=RESUMO!$I$2:$I$100)*(H79>=RESUMO!$K$2:$K$100)*(H79<=RESUMO!$L$2:$L$100), 0)), "R$ ", "")) ))))} -> 22.45 | K79: 0 | L79: =S79/H79 -> -0.076122234 | Q79: =U79/M79 -> #DIV/0! | R79: =(H79-(H79*I79)-J79-(C79*E79)+K79) -> 787.76 | S79: =R79-(C79-F79) -> -72.24 | T79: =(M79-(M79*N79)-O79-(C79*E79)+P79) -> -34.4 | U79: =T79-(C79-F79) -> -894.4
A80: VENTISOL | B80: AGRATTO-MOD-CAR12-02 | C80: 441.9 | D80: 13 | E80: 0.04 | F80: 0 | G80: 0 | H80: 622.91 | I80: 0.11 | J80: {=IF(H80<12.5, H80/2, IF(H80<29, 6.25, IF(H80<50, 6.5, IF(H80<79, 6.75, VALUE(SUBSTITUTE( INDEX(RESUMO!$J$2:$J$100, MATCH(1, (D80>=RESUMO!$H$2:$H$100)*(D80<=RESUMO!$I$2:$I$100)*(H80>=RESUMO!$K$2:$K$100)*(H80<=RESUMO!$L$2:$L$100), 0)), "R$ ", "")) ))))} -> 65.95 | K80: 0 | L80: =S80/H80 -> 0.046337192 | M80: 688.5 | N80: 0.16 | O80: {=IF(M80<12.5, 0, IF(M80<29, 6.25, IF(M80<50, 6.5, IF(M80<79, 6.75, VALUE(SUBSTITUTE( INDEX(RESUMO!$J$2:$J$100, MATCH(1, (D80>=RESUMO!$H$2:$H$100)*(D80<=RESUMO!$I$2:$I$100)*(M80>=RESUMO!$K$2:$K$100)*(M80<=RESUMO!$L$2:$L$100), 0)), "R$ ", "")) ))))} -> 65.95 | P80: 0 | Q80: =U80/M80 -> 0.076708787 | R80: =(H80-(H80*I80)-J80-(C80*E80)+K80) -> 470.7639 | S80: =R80-(C80-F80) -> 28.8639 | T80: =(M80-(M80*N80)-O80-(C80*E80)+P80) -> 494.714 | U80: =T80-(C80-F80) -> 52.814
A81: VENTISOL | B81: AGRATTO-MOD-CAR15-02 | C81: 504.9 | D81: 30 | E81: 0.04 | F81: 0 | G81: 0 | H81: 695.13 | I81: 0.11 | J81: {=IF(H81<12.5, H81/2, IF(H81<29, 6.25, IF(H81<50, 6.5, IF(H81<79, 6.75, VALUE(SUBSTITUTE( INDEX(RESUMO!$J$2:$J$100, MATCH(1, (D81>=RESUMO!$H$2:$H$100)*(D81<=RESUMO!$I$2:$I$100)*(H81>=RESUMO!$K$2:$K$100)*(H81<=RESUMO!$L$2:$L$100), 0)), "R$ ", "")) ))))} -> 98.95 | K81: 0 | L81: =S81/H81 -> -0.0077399911 | M81: 746.17 | N81: 0.16 | O81: {=IF(M81<12.5, 0, IF(M81<29, 6.25, IF(M81<50, 6.5, IF(M81<79, 6.75, VALUE(SUBSTITUTE( INDEX(RESUMO!$J$2:$J$100, MATCH(1, (D81>=RESUMO!$H$2:$H$100)*(D81<=RESUMO!$I$2:$I$100)*(M81>=RESUMO!$K$2:$K$100)*(M81<=RESUMO!$L$2:$L$100), 0)), "R$ ", "")) ))))} -> 98.95 | P81: 0 | Q81: =U81/M81 -> 0.0036677969 | R81: =(H81-(H81*I81)-J81-(C81*E81)+K81) -> 499.5197 | S81: =R81-(C81-F81) -> -5.3803 | T81: =(M81-(M81*N81)-O81-(C81*E81)+P81) -> 507.6368 | U81: =T81-(C81-F81) -> 2.7368
A82: POSITIVO | B82: INFINIX-8PRO-4-256GB | D82: 0.5 | E82: 0.04 | F82: 0 | G82: 0 | H82: 849 | I82: 0.11 | J82: {=IF(H82<12.5, H82/2, IF(H82<29, 6.25, IF(H82<50, 6.5, IF(H82<79, 6.75, VALUE(SUBSTITUTE( INDEX(RESUMO!$J$2:$J$100, MATCH(1, (D82>=RESUMO!$H$2:$H$100)*(D82<=RESUMO!$I$2:$I$100)*(H82>=RESUMO!$K$2:$K$100)*(H82<=RESUMO!$L$2:$L$100), 0)), "R$ ", "")) ))))} -> 21.45 | K82: 0 | L82: =S82/H82 -> 0.86473498 | Q82: =U82/M82 -> #DIV/0! | R82: =(H82-(H82*I82)-J82-(C82*E82)+K82) -> 734.16 | S82: =R82-(C82-F82) -> 734.16 | T82: =(M82-(M82*N82)-O82-(C82*E82)+P82) -> 0 | U82: =T82-(C82-F82) -> 0
A83: AOC | B83: AOC-43S5045-78 | C83: 1259.9 | D83: 17 | E83: 0.04 | F83: 0 | G83: 2 | H83: 1649 | I83: 0.11 | J83: {=IF(H83<12.5, H83/2, IF(H83<29, 6.25, IF(H83<50, 6.5, IF(H83<79, 6.75, VALUE(SUBSTITUTE( INDEX(RESUMO!$J$2:$J$100, MATCH(1, (D83>=RESUMO!$H$2:$H$100)*(D83<=RESUMO!$I$2:$I$100)*(H83>=RESUMO!$K$2:$K$100)*(H83<=RESUMO!$L$2:$L$100), 0)), "R$ ", "")) ))))} -> 73.45 | K83: 0 | L83: =S83/H83 -> 0.050857489 | M83: 1755 | N83: 0.16 | O83: {=IF(M83<12.5, 0, IF(M83<29, 6.25, IF(M83<50, 6.5, IF(M83<79, 6.75, VALUE(SUBSTITUTE( INDEX(RESUMO!$J$2:$J$100, MATCH(1, (D83>=RESUMO!$H$2:$H$100)*(D83<=RESUMO!$I$2:$I$100)*(M83>=RESUMO!$K$2:$K$100)*(M83<=RESUMO!$L$2:$L$100), 0)), "R$ ", "")) ))))} -> 73.45 | P83: 0 | Q83: =U83/M83 -> 0.051540741 | R83: =(H83-(H83*I83)-J83-(C83*E83)+K83) -> 1343.764 | S83: =R83-(C83-F83) -> 83.864 | T83: =(M83-(M83*N83)-O83-(C83*E83)+P83) -> 1350.354 | U83: =T83-(C83-F83) -> 90.454
A84: POSITIVO | B84: POSITIVO-T810C-2-32GB | C84: 526.93 | D84: 1 | E84: 0.04 | F84: 0 | G84: 2 | L84: =S84/H84 -> #DIV/0! | M84: 625 | N84: 0.16 | O84: {=IF(M84<12.5, 0, IF(M84<29, 6.25, IF(M84<50, 6.5, IF(M84<79, 6.75, VALUE(SUBSTITUTE( INDEX(RESUMO!$J$2:$J$100, MATCH(1, (D84>=RESUMO!$H$2:$H$100)*(D84<=RESUMO!$I$2:$I$100)*(M84>=RESUMO!$K$2:$K$100)*(M84<=RESUMO!$L$2:$L$100), 0)), "R$ ", "")) ))))} -> 22.45 | P84: 0 | Q84: =U84/M84 -> -0.07273152 | R84: =(H84-(H84*I84)-J84-(C84*E84)+K84) -> -21.0772 | S84: =R84-(C84-F84) -> -548.0072 | T84: =(M84-(M84*N84)-O84-(C84*E84)+P84) -> 481.4728 | U84: =T84-(C84-F84) -> -45.4572
A85: BRITANIA | B85: BRITANIA-BAF20A-220V | C85: 132.49 | D85: 9 | E85: 0.04 | F85: 0 | G85: 2 | H85: 205 | I85: 0.11 | J85: {=IF(H85<12.5, H85/2, IF(H85<29, 6.25, IF(H85<50, 6.5, IF(H85<79, 6.75, VALUE(SUBSTITUTE( INDEX(RESUMO!$J$2:$J$100, MATCH(1, (D85>=RESUMO!$H$2:$H$100)*(D85<=RESUMO!$I$2:$I$100)*(H85>=RESUMO!$K$2:$K$100)*(H85<=RESUMO!$L$2:$L$100), 0)), "R$ ", "")) ))))} -> 44.45 | K85: 0 | L85: =S85/H85 -> 0.0010263415 | M85: 219 | N85: 0.16 | O85: {=IF(M85<12.5, 0, IF(M85<29, 6.25, IF(M85<50, 6.5, IF(M85<79, 6.75, VALUE(SUBSTITUTE( INDEX(RESUMO!$J$2:$J$100, MATCH(1, (D85>=RESUMO!$H$2:$H$100)*(D85<=RESUMO!$I$2:$I$100)*(M85>=RESUMO!$K$2:$K$100)*(M85<=RESUMO!$L$2:$L$100), 0)), "R$ ", "")) ))))} -> 44.45 | P85: 0 | Q85: =U85/M85 -> 0.0078557078 | R85: =(H85-(H85*I85)-J85-(C85*E85)+K85) -> 132.7004 | S85: =R85-(C85-F85) -> 0.2104 | T85: =(M85-(M85*N85)-O85-(C85*E85)+P85) -> 134.2104 | U85: =T85-(C85-F85) -> 1.7204
A86: BRITANIA | B86: BRITANIA-BCX4600-BIV | C86: 300.43 | D86: 9 | E86: 0.04 | F86: 0 | G86: 2 | H86: 436 | I86: 0.13 | J86: {=IF(H86<12.5, H86/2, IF(H86<29, 6.25, IF(H86<50, 6.5, IF(H86<79, 6.75, VALUE(SUBSTITUTE( INDEX(RESUMO!$J$2:$J$100, MATCH(1, (D86>=RESUMO!$H$2:$H$100)*(D86<=RESUMO!$I$2:$I$100)*(H86>=RESUMO!$K$2:$K$100)*(H86<=RESUMO!$L$2:$L$100), 0)), "R$ ", "")) ))))} -> 44.45 | K86: 0 | L86: =S86/H86 -> 0.05142844 | M86: 465 | N86: 0.18 | O86: {=IF(M86<12.5, 0, IF(M86<29, 6.25, IF(M86<50, 6.5, IF(M86<79, 6.75, VALUE(SUBSTITUTE( INDEX(RESUMO!$J$2:$J$100, MATCH(1, (D86>=RESUMO!$H$2:$H$100)*(D86<=RESUMO!$I$2:$I$100)*(M86>=RESUMO!$K$2:$K$100)*(M86<=RESUMO!$L$2:$L$100), 0)), "R$ ", "")) ))))} -> 44.45 | P86: 0 | Q86: =U86/M86 -> 0.05247914 | R86: =(H86-(H86*I86)-J86-(C86*E86)+K86) -> 322.8528 | S86: =R86-(C86-F86) -> 22.4228 | T86: =(M86-(M86*N86)-O86-(C86*E86)+P86) -> 324.8328 | U86: =T86-(C86-F86) -> 24.4028
A87: POSITIVO | B87: POSITIVO-SMART-LUMINARIA-BIV | C87: 147.03 | D87: 1 | E87: 0.04 | F87: 0 | G87: 2 | H87: 211 | I87: 0.115 | J87: {=IF(H87<12.5, H87/2, IF(H87<29, 6.25, IF(H87<50, 6.5, IF(H87<79, 6.75, VALUE(SUBSTITUTE( INDEX(RESUMO!$J$2:$J$100, MATCH(1, (D87>=RESUMO!$H$2:$H$100)*(D87<=RESUMO!$I$2:$I$100)*(H87>=RESUMO!$K$2:$K$100)*(H87<=RESUMO!$L$2:$L$100), 0)), "R$ ", "")) ))))} -> 22.45 | K87: 0 | L87: =S87/H87 -> 0.053904265 | M87: 225 | N87: 0.165 | O87: {=IF(M87<12.5, 0, IF(M87<29, 6.25, IF(M87<50, 6.5, IF(M87<79, 6.75, VALUE(SUBSTITUTE( INDEX(RESUMO!$J$2:$J$100, MATCH(1, (D87>=RESUMO!$H$2:$H$100)*(D87<=RESUMO!$I$2:$I$100)*(M87>=RESUMO!$K$2:$K$100)*(M87<=RESUMO!$L$2:$L$100), 0)), "R$ ", "")) ))))} -> 22.45 | P87: 0 | Q87: =U87/M87 -> 0.055616889 | R87: =(H87-(H87*I87)-J87-(C87*E87)+K87) -> 158.4038 | S87: =R87-(C87-F87) -> 11.3738 | T87: =(M87-(M87*N87)-O87-(C87*E87)+P87) -> 159.5438 | U87: =T87-(C87-F87) -> 12.5138
A88: BRITANIA | B88: BRITANIA-JUICER700-220V | C88: 200.15 | D88: 5 | E88: 0.04 | F88: 0 | G88: 2 | H88: 266 | I88: 0.11 | J88: {=IF(H88<12.5, H88/2, IF(H88<29, 6.25, IF(H88<50, 6.5, IF(H88<79, 6.75, VALUE(SUBSTITUTE( INDEX(RESUMO!$J$2:$J$100, MATCH(1, (D88>=RESUMO!$H$2:$H$100)*(D88<=RESUMO!$I$2:$I$100)*(H88>=RESUMO!$K$2:$K$100)*(H88<=RESUMO!$L$2:$L$100), 0)), "R$ ", "")) ))))} -> 28.45 | K88: 0 | L88: =S88/H88 -> 0.0005037594 | M88: 285 | N88: 0.16 | O88: {=IF(M88<12.5, 0, IF(M88<29, 6.25, IF(M88<50, 6.5, IF(M88<79, 6.75, VALUE(SUBSTITUTE( INDEX(RESUMO!$J$2:$J$100, MATCH(1, (D88>=RESUMO!$H$2:$H$100)*(D88<=RESUMO!$I$2:$I$100)*(M88>=RESUMO!$K$2:$K$100)*(M88<=RESUMO!$L$2:$L$100), 0)), "R$ ", "")) ))))} -> 28.45 | P88: 0 | Q88: =U88/M88 -> 0.0098035088 | R88: =(H88-(H88*I88)-J88-(C88*E88)+K88) -> 200.284 | S88: =R88-(C88-F88) -> 0.134 | T88: =(M88-(M88*N88)-O88-(C88*E88)+P88) -> 202.944 | U88: =T88-(C88-F88) -> 2.794
A89: NAUTIKA | B89: NTK-GAS_227G | C89: 0 | D89: 0.3 | F89: 0 | G89: 2 | H89: 19.9 | I89: 0.12 | J89: {=IF(H89<12.5, H89/2, IF(H89<29, 6.25, IF(H89<50, 6.5, IF(H89<79, 6.75, VALUE(SUBSTITUTE( INDEX(RESUMO!$J$2:$J$100, MATCH(1, (D89>=RESUMO!$H$2:$H$100)*(D89<=RESUMO!$I$2:$I$100)*(H89>=RESUMO!$K$2:$K$100)*(H89<=RESUMO!$L$2:$L$100), 0)), "R$ ", "")) ))))} -> 6.25 | K89: 0 | L89: =S89/H89 -> #VALUE! | O89: {=IF(M89<12.5, 0, IF(M89<29, 6.25, IF(M89<50, 6.5, IF(M89<79, 6.75, VALUE(SUBSTITUTE( INDEX(RESUMO!$J$2:$J$100, MATCH(1, (D89>=RESUMO!$H$2:$H$100)*(D89<=RESUMO!$I$2:$I$100)*(M89>=RESUMO!$K$2:$K$100)*(M89<=RESUMO!$L$2:$L$100), 0)), "R$ ", "")) ))))} -> 0 | Q89: =U89/M89 -> #VALUE! | R89: =(H89-(H89*I89)-J89-(C89*E89)+K89) -> #VALUE! | S89: =R89-(C89-F89) -> #VALUE! | T89: =(M89-(M89*N89)-O89-(C89*E89)+P89) -> #VALUE! | U89: =T89-(C89-F89) -> #VALUE!
A90: NAUTIKA | B90: NTK-ROGUE-LIGHT-2L-VM | C90: 0 | D90: 2 | E90: 0.04 | F90: 0 | G90: 2 | H90: 549.9 | I90: 0.14 | J90: {=IF(H90<12.5, H90/2, IF(H90<29, 6.25, IF(H90<50, 6.5, IF(H90<79, 6.75, VALUE(SUBSTITUTE( INDEX(RESUMO!$J$2:$J$100, MATCH(1, (D90>=RESUMO!$H$2:$H$100)*(D90<=RESUMO!$I$2:$I$100)*(H90>=RESUMO!$K$2:$K$100)*(H90<=RESUMO!$L$2:$L$100), 0)), "R$ ", "")) ))))} -> 23.45 | K90: 0 | L90: =S90/H90 -> 0.81735588 | O90: {=IF(M90<12.5, 0, IF(M90<29, 6.25, IF(M90<50, 6.5, IF(M90<79, 6.75, VALUE(SUBSTITUTE( INDEX(RESUMO!$J$2:$J$100, MATCH(1, (D90>=RESUMO!$H$2:$H$100)*(D90<=RESUMO!$I$2:$I$100)*(M90>=RESUMO!$K$2:$K$100)*(M90<=RESUMO!$L$2:$L$100), 0)), "R$ ", "")) ))))} -> 0 | Q90: =U90/M90 -> #DIV/0! | R90: =(H90-(H90*I90)-J90-(C90*E90)+K90) -> 449.464 | S90: =R90-(C90-F90) -> 449.464 | T90: =(M90-(M90*N90)-O90-(C90*E90)+P90) -> 0 | U90: =T90-(C90-F90) -> 0
A91: NAUTIKA | B91: NTK-FRONTIER-FLEX-01B | C91: 0 | E91: 0.04 | F91: 0 | H91: 159.9 | I91: 0.115 | J91: {=IF(H91<12.5, H91/2, IF(H91<29, 6.25, IF(H91<50, 6.5, IF(H91<79, 6.75, VALUE(SUBSTITUTE( INDEX(RESUMO!$J$2:$J$100, MATCH(1, (D91>=RESUMO!$H$2:$H$100)*(D91<=RESUMO!$I$2:$I$100)*(H91>=RESUMO!$K$2:$K$100)*(H91<=RESUMO!$L$2:$L$100), 0)), "R$ ", "")) ))))} -> 17.95 | K91: 0 | L91: =S91/H91 -> 0.77274234 | O91: {=IF(M91<12.5, 0, IF(M91<29, 6.25, IF(M91<50, 6.5, IF(M91<79, 6.75, VALUE(SUBSTITUTE( INDEX(RESUMO!$J$2:$J$100, MATCH(1, (D91>=RESUMO!$H$2:$H$100)*(D91<=RESUMO!$I$2:$I$100)*(M91>=RESUMO!$K$2:$K$100)*(M91<=RESUMO!$L$2:$L$100), 0)), "R$ ", "")) ))))} -> 0 | Q91: =U91/M91 -> #DIV/0! | R91: =(H91-(H91*I91)-J91-(C91*E91)+K91) -> 123.5615 | S91: =R91-(C91-F91) -> 123.5615 | T91: =(M91-(M91*N91)-O91-(C91*E91)+P91) -> 0 | U91: =T91-(C91-F91) -> 0
A92: NAUTIKA | B92: NTK-FRONTIER-FLEX-2L-AZ | C92: 0 | E92: 0.04 | F92: 0 | H92: 144.9 | I92: 0.115 | J92: {=IF(H92<12.5, H92/2, IF(H92<29, 6.25, IF(H92<50, 6.5, IF(H92<79, 6.75, VALUE(SUBSTITUTE( INDEX(RESUMO!$J$2:$J$100, MATCH(1, (D92>=RESUMO!$H$2:$H$100)*(D92<=RESUMO!$I$2:$I$100)*(H92>=RESUMO!$K$2:$K$100)*(H92<=RESUMO!$L$2:$L$100), 0)), "R$ ", "")) ))))} -> 15.96 | K92: 0 | L92: =S92/H92 -> 0.77485507 | O92: {=IF(M92<12.5, 0, IF(M92<29, 6.25, IF(M92<50, 6.5, IF(M92<79, 6.75, VALUE(SUBSTITUTE( INDEX(RESUMO!$J$2:$J$100, MATCH(1, (D92>=RESUMO!$H$2:$H$100)*(D92<=RESUMO!$I$2:$I$100)*(M92>=RESUMO!$K$2:$K$100)*(M92<=RESUMO!$L$2:$L$100), 0)), "R$ ", "")) ))))} -> 0 | Q92: =U92/M92 -> #DIV/0! | R92: =(H92-(H92*I92)-J92-(C92*E92)+K92) -> 112.2765 | S92: =R92-(C92-F92) -> 112.2765 | T92: =(M92-(M92*N92)-O92-(C92*E92)+P92) -> 0 | U92: =T92-(C92-F92) -> 0
A93: NAUTIKA | B93: NTK-ARIA | C93: 0 | E93: 0.04 | F93: 0 | H93: 199.9 | I93: 0.115 | J93: {=IF(H93<12.5, H93/2, IF(H93<29, 6.25, IF(H93<50, 6.5, IF(H93<79, 6.75, VALUE(SUBSTITUTE( INDEX(RESUMO!$J$2:$J$100, MATCH(1, (D93>=RESUMO!$H$2:$H$100)*(D93<=RESUMO!$I$2:$I$100)*(H93>=RESUMO!$K$2:$K$100)*(H93<=RESUMO!$L$2:$L$100), 0)), "R$ ", "")) ))))} -> 17.95 | K93: 0 | L93: =S93/H93 -> 0.7952051 | O93: {=IF(M93<12.5, 0, IF(M93<29, 6.25, IF(M93<50, 6.5, IF(M93<79, 6.75, VALUE(SUBSTITUTE( INDEX(RESUMO!$J$2:$J$100, MATCH(1, (D93>=RESUMO!$H$2:$H$100)*(D93<=RESUMO!$I$2:$I$100)*(M93>=RESUMO!$K$2:$K$100)*(M93<=RESUMO!$L$2:$L$100), 0)), "R$ ", "")) ))))} -> 0 | Q93: =U93/M93 -> #DIV/0! | R93: =(H93-(H93*I93)-J93-(C93*E93)+K93) -> 158.9615 | S93: =R93-(C93-F93) -> 158.9615 | T93: =(M93-(M93*N93)-O93-(C93*E93)+P93) -> 0 | U93: =T93-(C93-F93) -> 0
A94: NAUTIKA | B94: NTK-LANTERNA-GUEPARDO | C94: 0 | D94: 1 | E94: 0.04 | F94: 0 | H94: 199.9 | I94: 0.115 | J94: {=IF(H94<12.5, H94/2, IF(H94<29, 6.25, IF(H94<50, 6.5, IF(H94<79, 6.75, VALUE(SUBSTITUTE( INDEX(RESUMO!$J$2:$J$100, MATCH(1, (D94>=RESUMO!$H$2:$H$100)*(D94<=RESUMO!$I$2:$I$100)*(H94>=RESUMO!$K$2:$K$100)*(H94<=RESUMO!$L$2:$L$100), 0)), "R$ ", "")) ))))} -> 20.2 | K94: 0 | L94: =S94/H94 -> 0.78394947 | O94: {=IF(M94<12.5, 0, IF(M94<29, 6.25, IF(M94<50, 6.5, IF(M94<79, 6.75, VALUE(SUBSTITUTE( INDEX(RESUMO!$J$2:$J$100, MATCH(1, (D94>=RESUMO!$H$2:$H$100)*(D94<=RESUMO!$I$2:$I$100)*(M94>=RESUMO!$K$2:$K$100)*(M94<=RESUMO!$L$2:$L$100), 0)), "R$ ", "")) ))))} -> 0 | Q94: =U94/M94 -> #DIV/0! | R94: =(H94-(H94*I94)-J94-(C94*E94)+K94) -> 156.7115 | S94: =R94-(C94-F94) -> 156.7115 | T94: =(M94-(M94*N94)-O94-(C94*E94)+P94) -> 0 | U94: =T94-(C94-F94) -> 0
A95: NAUTIKA | B95: NTK-GRILLMASTER | C95: 0 | E95: 0.04 | F95: 0 | H95: 449.9 | I95: 0.115 | J95: {=IF(H95<12.5, H95/2, IF(H95<29, 6.25, IF(H95<50, 6.5, IF(H95<79, 6.75, VALUE(SUBSTITUTE( INDEX(RESUMO!$J$2:$J$100, MATCH(1, (D95>=RESUMO!$H$2:$H$100)*(D95<=RESUMO!$I$2:$I$100)*(H95>=RESUMO!$K$2:$K$100)*(H95<=RESUMO!$L$2:$L$100), 0)), "R$ ", "")) ))))} -> 19.95 | K95: 0 | L95: =S95/H95 -> 0.84065681 | O95: {=IF(M95<12.5, 0, IF(M95<29, 6.25, IF(M95<50, 6.5, IF(M95<79, 6.75, VALUE(SUBSTITUTE( INDEX(RESUMO!$J$2:$J$100, MATCH(1, (D95>=RESUMO!$H$2:$H$100)*(D95<=RESUMO!$I$2:$I$100)*(M95>=RESUMO!$K$2:$K$100)*(M95<=RESUMO!$L$2:$L$100), 0)), "R$ ", "")) ))))} -> 0 | Q95: =U95/M95 -> #DIV/0! | R95: =(H95-(H95*I95)-J95-(C95*E95)+K95) -> 378.2115 | S95: =R95-(C95-F95) -> 378.2115 | T95: =(M95-(M95*N95)-O95-(C95*E95)+P95) -> 0 | U95: =T95-(C95-F95) -> 0
A96: NAUTIKA | B96: NTK-FOGAREIRO-GUEPARDO | C96: 0 | E96: 0.04 | F96: 0 | H96: 215 | I96: 0.115 | J96: {=IF(H96<12.5, H96/2, IF(H96<29, 6.25, IF(H96<50, 6.5, IF(H96<79, 6.75, VALUE(SUBSTITUTE( INDEX(RESUMO!$J$2:$J$100, MATCH(1, (D96>=RESUMO!$H$2:$H$100)*(D96<=RESUMO!$I$2:$I$100)*(H96>=RESUMO!$K$2:$K$100)*(H96<=RESUMO!$L$2:$L$100), 0)), "R$ ", "")) ))))} -> 19.95 | K96: 0 | L96: =S96/H96 -> 0.7922093 | O96: {=IF(M96<12.5, 0, IF(M96<29, 6.25, IF(M96<50, 6.5, IF(M96<79, 6.75, VALUE(SUBSTITUTE( INDEX(RESUMO!$J$2:$J$100, MATCH(1, (D96>=RESUMO!$H$2:$H$100)*(D96<=RESUMO!$I$2:$I$100)*(M96>=RESUMO!$K$2:$K$100)*(M96<=RESUMO!$L$2:$L$100), 0)), "R$ ", "")) ))))} -> 0 | Q96: =U96/M96 -> #DIV/0! | R96: =(H96-(H96*I96)-J96-(C96*E96)+K96) -> 170.325 | S96: =R96-(C96-F96) -> 170.325 | T96: =(M96-(M96*N96)-O96-(C96*E96)+P96) -> 0 | U96: =T96-(C96-F96) -> 0
A97: NAUTIKA | B97: NTK-AMOLADOR-SHARP | C97: 0 | D97: 0.3 | E97: 0.04 | F97: 0 | G97: 2 | H97: 44.9 | I97: 0.115 | J97: {=IF(H97<12.5, H97/2, IF(H97<29, 6.25, IF(H97<50, 6.5, IF(H97<79, 6.75, VALUE(SUBSTITUTE( INDEX(RESUMO!$J$2:$J$100, MATCH(1, (D97>=RESUMO!$H$2:$H$100)*(D97<=RESUMO!$I$2:$I$100)*(H97>=RESUMO!$K$2:$K$100)*(H97<=RESUMO!$L$2:$L$100), 0)), "R$ ", "")) ))))} -> 6.5 | K97: 0 | L97: =S97/H97 -> 0.74023385 | O97: {=IF(M97<12.5, 0, IF(M97<29, 6.25, IF(M97<50, 6.5, IF(M97<79, 6.75, VALUE(SUBSTITUTE( INDEX(RESUMO!$J$2:$J$100, MATCH(1, (D97>=RESUMO!$H$2:$H$100)*(D97<=RESUMO!$I$2:$I$100)*(M97>=RESUMO!$K$2:$K$100)*(M97<=RESUMO!$L$2:$L$100), 0)), "R$ ", "")) ))))} -> 0 | Q97: =U97/M97 -> #DIV/0! | R97: =(H97-(H97*I97)-J97-(C97*E97)+K97) -> 33.2365 | S97: =R97-(C97-F97) -> 33.2365 | T97: =(M97-(M97*N97)-O97-(C97*E97)+P97) -> 0 | U97: =T97-(C97-F97) -> 0
A98: NAUTIKA | B98: NTK-FOGAREIRO-JUPITER | C98: 0 | E98: 0.04 | F98: 0 | H98: 175 | I98: 0.115 | J98: {=IF(H98<12.5, H98/2, IF(H98<29, 6.25, IF(H98<50, 6.5, IF(H98<79, 6.75, VALUE(SUBSTITUTE( INDEX(RESUMO!$J$2:$J$100, MATCH(1, (D98>=RESUMO!$H$2:$H$100)*(D98<=RESUMO!$I$2:$I$100)*(H98>=RESUMO!$K$2:$K$100)*(H98<=RESUMO!$L$2:$L$100), 0)), "R$ ", "")) ))))} -> 17.95 | K98: 0 | L98: =S98/H98 -> 0.78242857 | O98: {=IF(M98<12.5, 0, IF(M98<29, 6.25, IF(M98<50, 6.5, IF(M98<79, 6.75, VALUE(SUBSTITUTE( INDEX(RESUMO!$J$2:$J$100, MATCH(1, (D98>=RESUMO!$H$2:$H$100)*(D98<=RESUMO!$I$2:$I$100)*(M98>=RESUMO!$K$2:$K$100)*(M98<=RESUMO!$L$2:$L$100), 0)), "R$ ", "")) ))))} -> 0 | Q98: =U98/M98 -> #DIV/0! | R98: =(H98-(H98*I98)-J98-(C98*E98)+K98) -> 136.925 | S98: =R98-(C98-F98) -> 136.925 | T98: =(M98-(M98*N98)-O98-(C98*E98)+P98) -> 0 | U98: =T98-(C98-F98) -> 0
B99: BRIGHT-AC587 | C99: 0 | D99: 0.3 | E99: 0.04 | F99: 0 | G99: 2 | H99: 74.9 | I99: 0.13 | J99: {=IF(H99<12.5, H99/2, IF(H99<29, 6.25, IF(H99<50, 6.5, IF(H99<79, 6.75, VALUE(SUBSTITUTE( INDEX(RESUMO!$J$2:$J$100, MATCH(1, (D99>=RESUMO!$H$2:$H$100)*(D99<=RESUMO!$I$2:$I$100)*(H99>=RESUMO!$K$2:$K$100)*(H99<=RESUMO!$L$2:$L$100), 0)), "R$ ", "")) ))))} -> 6.75 | K99: 0 | L99: =S99/H99 -> 0.77987984 | O99: {=IF(M99<12.5, 0, IF(M99<29, 6.25, IF(M99<50, 6.5, IF(M99<79, 6.75, VALUE(SUBSTITUTE( INDEX(RESUMO!$J$2:$J$100, MATCH(1, (D99>=RESUMO!$H$2:$H$100)*(D99<=RESUMO!$I$2:$I$100)*(M99>=RESUMO!$K$2:$K$100)*(M99<=RESUMO!$L$2:$L$100), 0)), "R$ ", "")) ))))} -> 0 | Q99: =U99/M99 -> #DIV/0! | R99: =(H99-(H99*I99)-J99-(C99*E99)+K99) -> 58.413 | S99: =R99-(C99-F99) -> 58.413 | T99: =(M99-(M99*N99)-O99-(C99*E99)+P99) -> 0 | U99: =T99-(C99-F99) -> 0
A100: TARGUS | B100: TARGUS-AWE804GL-50 | C100: 0 | E100: 0.04 | F100: 0 | H100: 149.9 | I100: 0.13 | J100: {=IF(H100<12.5, H100/2, IF(H100<29, 6.25, IF(H100<50, 6.5, IF(H100<79, 6.75, VALUE(SUBSTITUTE( INDEX(RESUMO!$J$2:$J$100, MATCH(1, (D100>=RESUMO!$H$2:$H$100)*(D100<=RESUMO!$I$2:$I$100)*(H100>=RESUMO!$K$2:$K$100)*(H100<=RESUMO!$L$2:$L$100), 0)), "R$ ", "")) ))))} -> 15.96 | K100: 0 | L100: =S100/H100 -> 0.76352902 | O100: {=IF(M100<12.5, 0, IF(M100<29, 6.25, IF(M100<50, 6.5, IF(M100<79, 6.75, VALUE(SUBSTITUTE( INDEX(RESUMO!$J$2:$J$100, MATCH(1, (D100>=RESUMO!$H$2:$H$100)*(D100<=RESUMO!$I$2:$I$100)*(M100>=RESUMO!$K$2:$K$100)*(M100<=RESUMO!$L$2:$L$100), 0)), "R$ ", "")) ))))} -> 0 | Q100: =U100/M100 -> #DIV/0! | R100: =(H100-(H100*I100)-J100-(C100*E100)+K100) -> 114.453 | S100: =R100-(C100-F100) -> 114.453 | T100: =(M100-(M100*N100)-O100-(C100*E100)+P100) -> 0 | U100: =T100-(C100-F100) -> 0
B101: FLEXINTER-T4-AZUL | C101: 0 | D101: 2 | E101: 0.04 | F101: 0 | G101: 2 | H101: 499 | I101: 0.11 | J101: {=IF(H101<12.5, H101/2, IF(H101<29, 6.25, IF(H101<50, 6.5, IF(H101<79, 6.75, VALUE(SUBSTITUTE( INDEX(RESUMO!$J$2:$J$100, MATCH(1, (D101>=RESUMO!$H$2:$H$100)*(D101<=RESUMO!$I$2:$I$100)*(H101>=RESUMO!$K$2:$K$100)*(H101<=RESUMO!$L$2:$L$100), 0)), "R$ ", "")) ))))} -> 23.45 | K101: 0 | L101: =S101/H101 -> 0.84300601 | O101: {=IF(M101<12.5, 0, IF(M101<29, 6.25, IF(M101<50, 6.5, IF(M101<79, 6.75, VALUE(SUBSTITUTE( INDEX(RESUMO!$J$2:$J$100, MATCH(1, (D101>=RESUMO!$H$2:$H$100)*(D101<=RESUMO!$I$2:$I$100)*(M101>=RESUMO!$K$2:$K$100)*(M101<=RESUMO!$L$2:$L$100), 0)), "R$ ", "")) ))))} -> 0 | Q101: =U101/M101 -> #DIV/0! | R101: =(H101-(H101*I101)-J101-(C101*E101)+K101) -> 420.66 | S101: =R101-(C101-F101) -> 420.66 | T101: =(M101-(M101*N101)-O101-(C101*E101)+P101) -> 0 | U101: =T101-(C101-F101) -> 0
B102: ELGIN-42MV4127-ROXA | C102: 0 | D102: 0.3 | E102: 0.04 | F102: 0 | G102: 2 | H102: 31.5 | I102: 0.115 | J102: {=IF(H102<12.5, H102/2, IF(H102<29, 6.25, IF(H102<50, 6.5, IF(H102<79, 6.75, VALUE(SUBSTITUTE( INDEX(RESUMO!$J$2:$J$100, MATCH(1, (D102>=RESUMO!$H$2:$H$100)*(D102<=RESUMO!$I$2:$I$100)*(H102>=RESUMO!$K$2:$K$100)*(H102<=RESUMO!$L$2:$L$100), 0)), "R$ ", "")) ))))} -> 6.5 | K102: 0 | L102: =S102/H102 -> 0.67865079 | O102: {=IF(M102<12.5, 0, IF(M102<29, 6.25, IF(M102<50, 6.5, IF(M102<79, 6.75, VALUE(SUBSTITUTE( INDEX(RESUMO!$J$2:$J$100, MATCH(1, (D102>=RESUMO!$H$2:$H$100)*(D102<=RESUMO!$I$2:$I$100)*(M102>=RESUMO!$K$2:$K$100)*(M102<=RESUMO!$L$2:$L$100), 0)), "R$ ", "")) ))))} -> 0 | Q102: =U102/M102 -> #DIV/0! | R102: =(H102-(H102*I102)-J102-(C102*E102)+K102) -> 21.3775 | S102: =R102-(C102-F102) -> 21.3775 | T102: =(M102-(M102*N102)-O102-(C102*E102)+P102) -> 0 | U102: =T102-(C102-F102) -> 0
B103: OCTOO-7898605650026 | C103: 0 | D103: 0.3 | E103: 0.04 | F103: 0 | G103: 2 | H103: 47.5 | I103: 0.13 | J103: {=IF(H103<12.5, H103/2, IF(H103<29, 6.25, IF(H103<50, 6.5, IF(H103<79, 6.75, VALUE(SUBSTITUTE( INDEX(RESUMO!$J$2:$J$100, MATCH(1, (D103>=RESUMO!$H$2:$H$100)*(D103<=RESUMO!$I$2:$I$100)*(H103>=RESUMO!$K$2:$K$100)*(H103<=RESUMO!$L$2:$L$100), 0)), "R$ ", "")) ))))} -> 6.5 | K103: 0 | L103: =S103/H103 -> 0.73315789 | O103: {=IF(M103<12.5, 0, IF(M103<29, 6.25, IF(M103<50, 6.5, IF(M103<79, 6.75, VALUE(SUBSTITUTE( INDEX(RESUMO!$J$2:$J$100, MATCH(1, (D103>=RESUMO!$H$2:$H$100)*(D103<=RESUMO!$I$2:$I$100)*(M103>=RESUMO!$K$2:$K$100)*(M103<=RESUMO!$L$2:$L$100), 0)), "R$ ", "")) ))))} -> 0 | Q103: =U103/M103 -> #DIV/0! | R103: =(H103-(H103*I103)-J103-(C103*E103)+K103) -> 34.825 | S103: =R103-(C103-F103) -> 34.825 | T103: =(M103-(M103*N103)-O103-(C103*E103)+P103) -> 0 | U103: =T103-(C103-F103) -> 0
B104: TOUGHBUILT-TB-KP-G203 | C104: 0 | D104: 4 | E104: 0.04 | F104: 0 | G104: 2 | H104: 459 | I104: 0.115 | J104: {=IF(H104<12.5, H104/2, IF(H104<29, 6.25, IF(H104<50, 6.5, IF(H104<79, 6.75, VALUE(SUBSTITUTE( INDEX(RESUMO!$J$2:$J$100, MATCH(1, (D104>=RESUMO!$H$2:$H$100)*(D104<=RESUMO!$I$2:$I$100)*(H104>=RESUMO!$K$2:$K$100)*(H104<=RESUMO!$L$2:$L$100), 0)), "R$ ", "")) ))))} -> 26.95 | K104: 0 | L104: =S104/H104 -> 0.8262854 | O104: {=IF(M104<12.5, 0, IF(M104<29, 6.25, IF(M104<50, 6.5, IF(M104<79, 6.75, VALUE(SUBSTITUTE( INDEX(RESUMO!$J$2:$J$100, MATCH(1, (D104>=RESUMO!$H$2:$H$100)*(D104<=RESUMO!$I$2:$I$100)*(M104>=RESUMO!$K$2:$K$100)*(M104<=RESUMO!$L$2:$L$100), 0)), "R$ ", "")) ))))} -> 0 | Q104: =U104/M104 -> #DIV/0! | R104: =(H104-(H104*I104)-J104-(C104*E104)+K104) -> 379.265 | S104: =R104-(C104-F104) -> 379.265 | T104: =(M104-(M104*N104)-O104-(C104*E104)+P104) -> 0 | U104: =T104-(C104-F104) -> 0
B105: TOUGHBUILT-TB-KP-102 | C105: 0 | D105: 3 | E105: 0.04 | F105: 0 | G105: 2 | H105: 225 | I105: 0.12 | J105: {=IF(H105<12.5, H105/2, IF(H105<29, 6.25, IF(H105<50, 6.5, IF(H105<79, 6.75, VALUE(SUBSTITUTE( INDEX(RESUMO!$J$2:$J$100, MATCH(1, (D105>=RESUMO!$H$2:$H$100)*(D105<=RESUMO!$I$2:$I$100)*(H105>=RESUMO!$K$2:$K$100)*(H105<=RESUMO!$L$2:$L$100), 0)), "R$ ", "")) ))))} -> 24.95 | K105: 0 | L105: =S105/H105 -> 0.76911111 | O105: {=IF(M105<12.5, 0, IF(M105<29, 6.25, IF(M105<50, 6.5, IF(M105<79, 6.75, VALUE(SUBSTITUTE( INDEX(RESUMO!$J$2:$J$100, MATCH(1, (D105>=RESUMO!$H$2:$H$100)*(D105<=RESUMO!$I$2:$I$100)*(M105>=RESUMO!$K$2:$K$100)*(M105<=RESUMO!$L$2:$L$100), 0)), "R$ ", "")) ))))} -> 0 | Q105: =U105/M105 -> #DIV/0! | R105: =(H105-(H105*I105)-J105-(C105*E105)+K105) -> 173.05 | S105: =R105-(C105-F105) -> 173.05 | T105: =(M105-(M105*N105)-O105-(C105*E105)+P105) -> 0 | U105: =T105-(C105-F105) -> 0
B106: TOUGHBUILT-TB-H4S30-80 | C106: 0 | D106: 0.3 | E106: 0.04 | F106: 0 | G106: 2 | H106: 59.9 | I106: 0.115 | J106: {=IF(H106<12.5, H106/2, IF(H106<29, 6.25, IF(H106<50, 6.5, IF(H106<79, 6.75, VALUE(SUBSTITUTE( INDEX(RESUMO!$J$2:$J$100, MATCH(1, (D106>=RESUMO!$H$2:$H$100)*(D106<=RESUMO!$I$2:$I$100)*(H106>=RESUMO!$K$2:$K$100)*(H106<=RESUMO!$L$2:$L$100), 0)), "R$ ", "")) ))))} -> 6.75 | K106: 0 | L106: =S106/H106 -> 0.77231219 | O106: {=IF(M106<12.5, 0, IF(M106<29, 6.25, IF(M106<50, 6.5, IF(M106<79, 6.75, VALUE(SUBSTITUTE( INDEX(RESUMO!$J$2:$J$100, MATCH(1, (D106>=RESUMO!$H$2:$H$100)*(D106<=RESUMO!$I$2:$I$100)*(M106>=RESUMO!$K$2:$K$100)*(M106<=RESUMO!$L$2:$L$100), 0)), "R$ ", "")) ))))} -> 0 | Q106: =U106/M106 -> #DIV/0! | R106: =(H106-(H106*I106)-J106-(C106*E106)+K106) -> 46.2615 | S106: =R106-(C106-F106) -> 46.2615 | T106: =(M106-(M106*N106)-O106-(C106*E106)+P106) -> 0 | U106: =T106-(C106-F106) -> 0
B107: TOUGHBUILT-TB-71-14 | C107: 0 | D107: 9 | E107: 0.04 | F107: 0 | G107: 2 | H107: 999 | I107: 0.12 | J107: {=IF(H107<12.5, H107/2, IF(H107<29, 6.25, IF(H107<50, 6.5, IF(H107<79, 6.75, VALUE(SUBSTITUTE( INDEX(RESUMO!$J$2:$J$100, MATCH(1, (D107>=RESUMO!$H$2:$H$100)*(D107<=RESUMO!$I$2:$I$100)*(H107>=RESUMO!$K$2:$K$100)*(H107<=RESUMO!$L$2:$L$100), 0)), "R$ ", "")) ))))} -> 44.45 | K107: 0 | L107: =S107/H107 -> 0.83550551 | O107: {=IF(M107<12.5, 0, IF(M107<29, 6.25, IF(M107<50, 6.5, IF(M107<79, 6.75, VALUE(SUBSTITUTE( INDEX(RESUMO!$J$2:$J$100, MATCH(1, (D107>=RESUMO!$H$2:$H$100)*(D107<=RESUMO!$I$2:$I$100)*(M107>=RESUMO!$K$2:$K$100)*(M107<=RESUMO!$L$2:$L$100), 0)), "R$ ", "")) ))))} -> 0 | Q107: =U107/M107 -> #DIV/0! | R107: =(H107-(H107*I107)-J107-(C107*E107)+K107) -> 834.67 | S107: =R107-(C107-F107) -> 834.67 | T107: =(M107-(M107*N107)-O107-(C107*E107)+P107) -> 0 | U107: =T107-(C107-F107) -> 0
B108: TOUGHBUILT-TB-KP-G201 | C108: 0 | D108: 4 | E108: 0.04 | F108: 0 | G108: 2 | H108: 389 | I108: 0.115 | J108: {=IF(H108<12.5, H108/2, IF(H108<29, 6.25, IF(H108<50, 6.5, IF(H108<79, 6.75, VALUE(SUBSTITUTE( INDEX(RESUMO!$J$2:$J$100, MATCH(1, (D108>=RESUMO!$H$2:$H$100)*(D108<=RESUMO!$I$2:$I$100)*(H108>=RESUMO!$K$2:$K$100)*(H108<=RESUMO!$L$2:$L$100), 0)), "R$ ", "")) ))))} -> 26.95 | K108: 0 | L108: =S108/H108 -> 0.81571979 | O108: {=IF(M108<12.5, 0, IF(M108<29, 6.25, IF(M108<50, 6.5, IF(M108<79, 6.75, VALUE(SUBSTITUTE( INDEX(RESUMO!$J$2:$J$100, MATCH(1, (D108>=RESUMO!$H$2:$H$100)*(D108<=RESUMO!$I$2:$I$100)*(M108>=RESUMO!$K$2:$K$100)*(M108<=RESUMO!$L$2:$L$100), 0)), "R$ ", "")) ))))} -> 0 | Q108: =U108/M108 -> #DIV/0! | R108: =(H108-(H108*I108)-J108-(C108*E108)+K108) -> 317.315 | S108: =R108-(C108-F108) -> 317.315 | T108: =(M108-(M108*N108)-O108-(C108*E108)+P108) -> 0 | U108: =T108-(C108-F108) -> 0
B109: TOUGHBUILT-TB-H4-60-SL | C109: 0 | D109: 1 | E109: 0.04 | F109: 0 | G109: 2 | H109: 239 | I109: 0.12 | J109: {=IF(H109<12.5, H109/2, IF(H109<29, 6.25, IF(H109<50, 6.5, IF(H109<79, 6.75, VALUE(SUBSTITUTE( INDEX(RESUMO!$J$2:$J$100, MATCH(1, (D109>=RESUMO!$H$2:$H$100)*(D109<=RESUMO!$I$2:$I$100)*(H109>=RESUMO!$K$2:$K$100)*(H109<=RESUMO!$L$2:$L$100), 0)), "R$ ", "")) ))))} -> 22.45 | K109: 0 | L109: =S109/H109 -> 0.78606695 | O109: {=IF(M109<12.5, 0, IF(M109<29, 6.25, IF(M109<50, 6.5, IF(M109<79, 6.75, VALUE(SUBSTITUTE( INDEX(RESUMO!$J$2:$J$100, MATCH(1, (D109>=RESUMO!$H$2:$H$100)*(D109<=RESUMO!$I$2:$I$100)*(M109>=RESUMO!$K$2:$K$100)*(M109<=RESUMO!$L$2:$L$100), 0)), "R$ ", "")) ))))} -> 0 | Q109: =U109/M109 -> #DIV/0! | R109: =(H109-(H109*I109)-J109-(C109*E109)+K109) -> 187.87 | S109: =R109-(C109-F109) -> 187.87 | T109: =(M109-(M109*N109)-O109-(C109*E109)+P109) -> 0 | U109: =T109-(C109-F109) -> 0
B110: TOUGHBUILT-TB-KP-G3 | C110: 0 | D110: 5 | E110: 0.04 | F110: 0 | G110: 2 | H110: 749.9 | I110: 0.115 | J110: {=IF(H110<12.5, H110/2, IF(H110<29, 6.25, IF(H110<50, 6.5, IF(H110<79, 6.75, VALUE(SUBSTITUTE( INDEX(RESUMO!$J$2:$J$100, MATCH(1, (D110>=RESUMO!$H$2:$H$100)*(D110<=RESUMO!$I$2:$I$100)*(H110>=RESUMO!$K$2:$K$100)*(H110<=RESUMO!$L$2:$L$100), 0)), "R$ ", "")) ))))} -> 28.45 | K110: 0 | L110: =S110/H110 -> 0.84706161 | O110: {=IF(M110<12.5, 0, IF(M110<29, 6.25, IF(M110<50, 6.5, IF(M110<79, 6.75, VALUE(SUBSTITUTE( INDEX(RESUMO!$J$2:$J$100, MATCH(1, (D110>=RESUMO!$H$2:$H$100)*(D110<=RESUMO!$I$2:$I$100)*(M110>=RESUMO!$K$2:$K$100)*(M110<=RESUMO!$L$2:$L$100), 0)), "R$ ", "")) ))))} -> 0 | Q110: =U110/M110 -> #DIV/0! | R110: =(H110-(H110*I110)-J110-(C110*E110)+K110) -> 635.2115 | S110: =R110-(C110-F110) -> 635.2115 | T110: =(M110-(M110*N110)-O110-(C110*E110)+P110) -> 0 | U110: =T110-(C110-F110) -> 0
B111: TOUGHBUILT-TB-53 | C111: 0 | E111: 0.04 | F111: 0 | H111: 179 | I111: 0.12 | J111: {=IF(H111<12.5, H111/2, IF(H111<29, 6.25, IF(H111<50, 6.5, IF(H111<79, 6.75, VALUE(SUBSTITUTE( INDEX(RESUMO!$J$2:$J$100, MATCH(1, (D111>=RESUMO!$H$2:$H$100)*(D111<=RESUMO!$I$2:$I$100)*(H111>=RESUMO!$K$2:$K$100)*(H111<=RESUMO!$L$2:$L$100), 0)), "R$ ", "")) ))))} -> 17.95 | K111: 0 | L111: =S111/H111 -> 0.77972067 | O111: {=IF(M111<12.5, 0, IF(M111<29, 6.25, IF(M111<50, 6.5, IF(M111<79, 6.75, VALUE(SUBSTITUTE( INDEX(RESUMO!$J$2:$J$100, MATCH(1, (D111>=RESUMO!$H$2:$H$100)*(D111<=RESUMO!$I$2:$I$100)*(M111>=RESUMO!$K$2:$K$100)*(M111<=RESUMO!$L$2:$L$100), 0)), "R$ ", "")) ))))} -> 0 | Q111: =U111/M111 -> #DIV/0! | R111: =(H111-(H111*I111)-J111-(C111*E111)+K111) -> 139.57 | S111: =R111-(C111-F111) -> 139.57 | T111: =(M111-(M111*N111)-O111-(C111*E111)+P111) -> 0 | U111: =T111-(C111-F111) -> 0
B112: TOUGHBUILT-TB-H4S-40-IK-2 | C112: 0 | E112: 0.04 | F112: 0 | H112: 189 | I112: 0.115 | J112: {=IF(H112<12.5, H112/2, IF(H112<29, 6.25, IF(H112<50, 6.5, IF(H112<79, 6.75, VALUE(SUBSTITUTE( INDEX(RESUMO!$J$2:$J$100, MATCH(1, (D112>=RESUMO!$H$2:$H$100)*(D112<=RESUMO!$I$2:$I$100)*(H112>=RESUMO!$K$2:$K$100)*(H112<=RESUMO!$L$2:$L$100), 0)), "R$ ", "")) ))))} -> 17.95 | K112: 0 | L112: =S112/H112 -> 0.79002646 | O112: {=IF(M112<12.5, 0, IF(M112<29, 6.25, IF(M112<50, 6.5, IF(M112<79, 6.75, VALUE(SUBSTITUTE( INDEX(RESUMO!$J$2:$J$100, MATCH(1, (D112>=RESUMO!$H$2:$H$100)*(D112<=RESUMO!$I$2:$I$100)*(M112>=RESUMO!$K$2:$K$100)*(M112<=RESUMO!$L$2:$L$100), 0)), "R$ ", "")) ))))} -> 0 | Q112: =U112/M112 -> #DIV/0! | R112: =(H112-(H112*I112)-J112-(C112*E112)+K112) -> 149.315 | S112: =R112-(C112-F112) -> 149.315 | T112: =(M112-(M112*N112)-O112-(C112*E112)+P112) -> 0 | U112: =T112-(C112-F112) -> 0
B113: TOUGHBUILT-TB-45G-M | C113: 0 | E113: 0.04 | F113: 0 | H113: 242 | I113: 0.14 | J113: {=IF(H113<12.5, H113/2, IF(H113<29, 6.25, IF(H113<50, 6.5, IF(H113<79, 6.75, VALUE(SUBSTITUTE( INDEX(RESUMO!$J$2:$J$100, MATCH(1, (D113>=RESUMO!$H$2:$H$100)*(D113<=RESUMO!$I$2:$I$100)*(H113>=RESUMO!$K$2:$K$100)*(H113<=RESUMO!$L$2:$L$100), 0)), "R$ ", "")) ))))} -> 19.95 | K113: 0 | L113: =S113/H113 -> 0.77756198 | O113: {=IF(M113<12.5, 0, IF(M113<29, 6.25, IF(M113<50, 6.5, IF(M113<79, 6.75, VALUE(SUBSTITUTE( INDEX(RESUMO!$J$2:$J$100, MATCH(1, (D113>=RESUMO!$H$2:$H$100)*(D113<=RESUMO!$I$2:$I$100)*(M113>=RESUMO!$K$2:$K$100)*(M113<=RESUMO!$L$2:$L$100), 0)), "R$ ", "")) ))))} -> 0 | Q113: =U113/M113 -> #DIV/0! | R113: =(H113-(H113*I113)-J113-(C113*E113)+K113) -> 188.17 | S113: =R113-(C113-F113) -> 188.17 | T113: =(M113-(M113*N113)-O113-(C113*E113)+P113) -> 0 | U113: =T113-(C113-F113) -> 0
B114: TOUGHBUILT-TB-45G-L | C114: 0 | E114: 0.04 | F114: 0 | H114: 245 | I114: 0.12 | J114: {=IF(H114<12.5, H114/2, IF(H114<29, 6.25, IF(H114<50, 6.5, IF(H114<79, 6.75, VALUE(SUBSTITUTE( INDEX(RESUMO!$J$2:$J$100, MATCH(1, (D114>=RESUMO!$H$2:$H$100)*(D114<=RESUMO!$I$2:$I$100)*(H114>=RESUMO!$K$2:$K$100)*(H114<=RESUMO!$L$2:$L$100), 0)), "R$ ", "")) ))))} -> 19.95 | K114: 0 | L114: =S114/H114 -> 0.79857143 | O114: {=IF(M114<12.5, 0, IF(M114<29, 6.25, IF(M114<50, 6.5, IF(M114<79, 6.75, VALUE(SUBSTITUTE( INDEX(RESUMO!$J$2:$J$100, MATCH(1, (D114>=RESUMO!$H$2:$H$100)*(D114<=RESUMO!$I$2:$I$100)*(M114>=RESUMO!$K$2:$K$100)*(M114<=RESUMO!$L$2:$L$100), 0)), "R$ ", "")) ))))} -> 0 | Q114: =U114/M114 -> #DIV/0! | R114: =(H114-(H114*I114)-J114-(C114*E114)+K114) -> 195.65 | S114: =R114-(C114-F114) -> 195.65 | T114: =(M114-(M114*N114)-O114-(C114*E114)+P114) -> 0 | U114: =T114-(C114-F114) -> 0
A115: FISCHER | B115: FISCHER-36340-102674-BIV | C115: 560.88 | D115: 9 | E115: 0.04 | F115: 0 | G115: 2 | H115: 749 | I115: 0.11 | J115: {=IF(H115<12.5, H115/2, IF(H115<29, 6.25, IF(H115<50, 6.5, IF(H115<79, 6.75, VALUE(SUBSTITUTE( INDEX(RESUMO!$J$2:$J$100, MATCH(1, (D115>=RESUMO!$H$2:$H$100)*(D115<=RESUMO!$I$2:$I$100)*(H115>=RESUMO!$K$2:$K$100)*(H115<=RESUMO!$L$2:$L$100), 0)), "R$ ", "")) ))))} -> 44.45 | K115: 0 | L115: =S115/H115 -> 0.051862216 | M115: 915 | N115: 0.16 | O115: {=IF(M115<12.5, 0, IF(M115<29, 6.25, IF(M115<50, 6.5, IF(M115<79, 6.75, VALUE(SUBSTITUTE( INDEX(RESUMO!$J$2:$J$100, MATCH(1, (D115>=RESUMO!$H$2:$H$100)*(D115<=RESUMO!$I$2:$I$100)*(M115>=RESUMO!$K$2:$K$100)*(M115<=RESUMO!$L$2:$L$100), 0)), "R$ ", "")) ))))} -> 44.45 | P115: 0 | Q115: =U115/M115 -> 0.15391781 | R115: =(H115-(H115*I115)-J115-(C115*E115)+K115) -> 599.7248 | S115: =R115-(C115-F115) -> 38.8448 | T115: =(M115-(M115*N115)-O115-(C115*E115)+P115) -> 701.7148 | U115: =T115-(C115-F115) -> 140.8348
A116: FISCHER | B116: FISCHER-33810-92122 | C116: 1274.54 | E116: 0.04 | F116: 0 | H116: 1915 | I116: 0.11 | J116: {=IF(H116<12.5, H116/2, IF(H116<29, 6.25, IF(H116<50, 6.5, IF(H116<79, 6.75, VALUE(SUBSTITUTE( INDEX(RESUMO!$J$2:$J$100, MATCH(1, (D116>=RESUMO!$H$2:$H$100)*(D116<=RESUMO!$I$2:$I$100)*(H116>=RESUMO!$K$2:$K$100)*(H116<=RESUMO!$L$2:$L$100), 0)), "R$ ", "")) ))))} -> 19.95 | K116: 0 | L116: =S116/H116 -> 0.18740386 | M116: 2049 | N116: 0.16 | O116: {=IF(M116<12.5, 0, IF(M116<29, 6.25, IF(M116<50, 6.5, IF(M116<79, 6.75, VALUE(SUBSTITUTE( INDEX(RESUMO!$J$2:$J$100, MATCH(1, (D116>=RESUMO!$H$2:$H$100)*(D116<=RESUMO!$I$2:$I$100)*(M116>=RESUMO!$K$2:$K$100)*(M116<=RESUMO!$L$2:$L$100), 0)), "R$ ", "")) ))))} -> 19.95 | P116: 0 | Q116: =U116/M116 -> 0.18335207 | R116: =(H116-(H116*I116)-J116-(C116*E116)+K116) -> 1633.4184 | S116: =R116-(C116-F116) -> 358.8784 | T116: =(M116-(M116*N116)-O116-(C116*E116)+P116) -> 1650.2284 | U116: =T116-(C116-F116) -> 375.6884
A117: FISCHER | B117: FISCHER-1642-6985-PT-BIV | C117: 445.29 | E117: 0.04 | F117: 0 | H117: 725 | I117: 0.11 | J117: {=IF(H117<12.5, H117/2, IF(H117<29, 6.25, IF(H117<50, 6.5, IF(H117<79, 6.75, VALUE(SUBSTITUTE( INDEX(RESUMO!$J$2:$J$100, MATCH(1, (D117>=RESUMO!$H$2:$H$100)*(D117<=RESUMO!$I$2:$I$100)*(H117>=RESUMO!$K$2:$K$100)*(H117<=RESUMO!$L$2:$L$100), 0)), "R$ ", "")) ))))} -> 19.95 | K117: 0 | L117: =S117/H117 -> 0.22372193 | M117: 775 | N117: 0.16 | O117: {=IF(M117<12.5, 0, IF(M117<29, 6.25, IF(M117<50, 6.5, IF(M117<79, 6.75, VALUE(SUBSTITUTE( INDEX(RESUMO!$J$2:$J$100, MATCH(1, (D117>=RESUMO!$H$2:$H$100)*(D117<=RESUMO!$I$2:$I$100)*(M117>=RESUMO!$K$2:$K$100)*(M117<=RESUMO!$L$2:$L$100), 0)), "R$ ", "")) ))))} -> 19.95 | P117: 0 | Q117: =U117/M117 -> 0.21670761 | R117: =(H117-(H117*I117)-J117-(C117*E117)+K117) -> 607.4884 | S117: =R117-(C117-F117) -> 162.1984 | T117: =(M117-(M117*N117)-O117-(C117*E117)+P117) -> 613.2384 | U117: =T117-(C117-F117) -> 167.9484
A118: FISCHER | B118: FISCHER-26298-57077-BIV | C118: 784.06 | E118: 0.04 | F118: 0 | H118: 1199 | I118: 0.11 | J118: {=IF(H118<12.5, H118/2, IF(H118<29, 6.25, IF(H118<50, 6.5, IF(H118<79, 6.75, VALUE(SUBSTITUTE( INDEX(RESUMO!$J$2:$J$100, MATCH(1, (D118>=RESUMO!$H$2:$H$100)*(D118<=RESUMO!$I$2:$I$100)*(H118>=RESUMO!$K$2:$K$100)*(H118<=RESUMO!$L$2:$L$100), 0)), "R$ ", "")) ))))} -> 19.95 | K118: 0 | L118: =S118/H118 -> 0.19327573 | M118: 1299 | N118: 0.16 | O118: {=IF(M118<12.5, 0, IF(M118<29, 6.25, IF(M118<50, 6.5, IF(M118<79, 6.75, VALUE(SUBSTITUTE( INDEX(RESUMO!$J$2:$J$100, MATCH(1, (D118>=RESUMO!$H$2:$H$100)*(D118<=RESUMO!$I$2:$I$100)*(M118>=RESUMO!$K$2:$K$100)*(M118<=RESUMO!$L$2:$L$100), 0)), "R$ ", "")) ))))} -> 19.95 | P118: 0 | Q118: =U118/M118 -> 0.19691116 | R118: =(H118-(H118*I118)-J118-(C118*E118)+K118) -> 1015.7976 | S118: =R118-(C118-F118) -> 231.7376 | T118: =(M118-(M118*N118)-O118-(C118*E118)+P118) -> 1039.8476 | U118: =T118-(C118-F118) -> 255.7876
A119: FISCHER | B119: FISCHER-26343-57174-BIV | C119: 473.9 | E119: 0.04 | F119: 0 | H119: 765 | I119: 0.11 | J119: {=IF(H119<12.5, H119/2, IF(H119<29, 6.25, IF(H119<50, 6.5, IF(H119<79, 6.75, VALUE(SUBSTITUTE( INDEX(RESUMO!$J$2:$J$100, MATCH(1, (D119>=RESUMO!$H$2:$H$100)*(D119<=RESUMO!$I$2:$I$100)*(H119>=RESUMO!$K$2:$K$100)*(H119<=RESUMO!$L$2:$L$100), 0)), "R$ ", "")) ))))} -> 19.95 | K119: 0 | L119: =S119/H119 -> 0.21966536 | M119: 825 | N119: 0.16 | O119: {=IF(M119<12.5, 0, IF(M119<29, 6.25, IF(M119<50, 6.5, IF(M119<79, 6.75, VALUE(SUBSTITUTE( INDEX(RESUMO!$J$2:$J$100, MATCH(1, (D119>=RESUMO!$H$2:$H$100)*(D119<=RESUMO!$I$2:$I$100)*(M119>=RESUMO!$K$2:$K$100)*(M119<=RESUMO!$L$2:$L$100), 0)), "R$ ", "")) ))))} -> 19.95 | P119: 0 | Q119: =U119/M119 -> 0.21841697 | R119: =(H119-(H119*I119)-J119-(C119*E119)+K119) -> 641.944 | S119: =R119-(C119-F119) -> 168.044 | T119: =(M119-(M119*N119)-O119-(C119*E119)+P119) -> 654.094 | U119: =T119-(C119-F119) -> 180.194
A120: FISCHER | B120: FISCHER-36360-102676-BIV | C120: 392.93 | E120: 0.04 | F120: 0 | H120: 649 | I120: 0.11 | J120: {=IF(H120<12.5, H120/2, IF(H120<29, 6.25, IF(H120<50, 6.5, IF(H120<79, 6.75, VALUE(SUBSTITUTE( INDEX(RESUMO!$J$2:$J$100, MATCH(1, (D120>=RESUMO!$H$2:$H$100)*(D120<=RESUMO!$I$2:$I$100)*(H120>=RESUMO!$K$2:$K$100)*(H120<=RESUMO!$L$2:$L$100), 0)), "R$ ", "")) ))))} -> 19.95 | K120: 0 | L120: =S120/H120 -> 0.2296037 | M120: 699 | N120: 0.16 | O120: {=IF(M120<12.5, 0, IF(M120<29, 6.25, IF(M120<50, 6.5, IF(M120<79, 6.75, VALUE(SUBSTITUTE( INDEX(RESUMO!$J$2:$J$100, MATCH(1, (D120>=RESUMO!$H$2:$H$100)*(D120<=RESUMO!$I$2:$I$100)*(M120>=RESUMO!$K$2:$K$100)*(M120<=RESUMO!$L$2:$L$100), 0)), "R$ ", "")) ))))} -> 19.95 | P120: 0 | Q120: =U120/M120 -> 0.22684235 | R120: =(H120-(H120*I120)-J120-(C120*E120)+K120) -> 541.9428 | S120: =R120-(C120-F120) -> 149.0128 | T120: =(M120-(M120*N120)-O120-(C120*E120)+P120) -> 551.4928 | U120: =T120-(C120-F120) -> 158.5628
A121: FISCHER | B121: FISCHER-23678-54121-BIV | C121: 862.51 | E121: 0.04 | F121: 0 | H121: 1349 | I121: 0.11 | J121: {=IF(H121<12.5, H121/2, IF(H121<29, 6.25, IF(H121<50, 6.5, IF(H121<79, 6.75, VALUE(SUBSTITUTE( INDEX(RESUMO!$J$2:$J$100, MATCH(1, (D121>=RESUMO!$H$2:$H$100)*(D121<=RESUMO!$I$2:$I$100)*(H121>=RESUMO!$K$2:$K$100)*(H121<=RESUMO!$L$2:$L$100), 0)), "R$ ", "")) ))))} -> 19.95 | K121: 0 | L121: =S121/H121 -> 0.21026657 | M121: 1399 | N121: 0.16 | O121: {=IF(M121<12.5, 0, IF(M121<29, 6.25, IF(M121<50, 6.5, IF(M121<79, 6.75, VALUE(SUBSTITUTE( INDEX(RESUMO!$J$2:$J$100, MATCH(1, (D121>=RESUMO!$H$2:$H$100)*(D121<=RESUMO!$I$2:$I$100)*(M121>=RESUMO!$K$2:$K$100)*(M121<=RESUMO!$L$2:$L$100), 0)), "R$ ", "")) ))))} -> 19.95 | P121: 0 | Q121: =U121/M121 -> 0.18456011 | R121: =(H121-(H121*I121)-J121-(C121*E121)+K121) -> 1146.1596 | S121: =R121-(C121-F121) -> 283.6496 | T121: =(M121-(M121*N121)-O121-(C121*E121)+P121) -> 1120.7096 | U121: =T121-(C121-F121) -> 258.1996
A122: FISCHER | B122: FISCHER-36310-102671-BIV | C122: 392.93 | E122: 0.04 | F122: 0 | J122: {=IF(H122<12.5, H122/2, IF(H122<29, 6.25, IF(H122<50, 6.5, IF(H122<79, 6.75, VALUE(SUBSTITUTE( INDEX(RESUMO!$J$2:$J$100, MATCH(1, (D122>=RESUMO!$H$2:$H$100)*(D122<=RESUMO!$I$2:$I$100)*(H122>=RESUMO!$K$2:$K$100)*(H122<=RESUMO!$L$2:$L$100), 0)), "R$ ", "")) ))))} -> 0 | K122: 0 | L122: =S122/H122 -> #DIV/0! | O122: {=IF(M122<12.5, 0, IF(M122<29, 6.25, IF(M122<50, 6.5, IF(M122<79, 6.75, VALUE(SUBSTITUTE( INDEX(RESUMO!$J$2:$J$100, MATCH(1, (D122>=RESUMO!$H$2:$H$100)*(D122<=RESUMO!$I$2:$I$100)*(M122>=RESUMO!$K$2:$K$100)*(M122<=RESUMO!$L$2:$L$100), 0)), "R$ ", "")) ))))} -> 0 | P122: 0 | Q122: =U122/M122 -> #DIV/0! | R122: =(H122-(H122*I122)-J122-(C122*E122)+K122) -> -15.7172 | S122: =R122-(C122-F122) -> -408.6472 | T122: =(M122-(M122*N122)-O122-(C122*E122)+P122) -> -15.7172 | U122: =T122-(C122-F122) -> -408.6472
A123: POSITIVO | B123: POSITIVO-T307SPF-3-64GB | C123: 379.63 | E123: 0.04 | F123: 0 | H123: 549 | I123: 0.11 | J123: {=IF(H123<12.5, H123/2, IF(H123<29, 6.25, IF(H123<50, 6.5, IF(H123<79, 6.75, VALUE(SUBSTITUTE( INDEX(RESUMO!$J$2:$J$100, MATCH(1, (D123>=RESUMO!$H$2:$H$100)*(D123<=RESUMO!$I$2:$I$100)*(H123>=RESUMO!$K$2:$K$100)*(H123<=RESUMO!$L$2:$L$100), 0)), "R$ ", "")) ))))} -> 19.95 | K123: 0 | L123: =S123/H123 -> 0.13450783 | M123: 599 | N123: 0.16 | O123: {=IF(M123<12.5, 0, IF(M123<29, 6.25, IF(M123<50, 6.5, IF(M123<79, 6.75, VALUE(SUBSTITUTE( INDEX(RESUMO!$J$2:$J$100, MATCH(1, (D123>=RESUMO!$H$2:$H$100)*(D123<=RESUMO!$I$2:$I$100)*(M123>=RESUMO!$K$2:$K$100)*(M123<=RESUMO!$L$2:$L$100), 0)), "R$ ", "")) ))))} -> 19.95 | P123: 0 | Q123: =U123/M123 -> 0.14757062 | R123: =(H123-(H123*I123)-J123-(C123*E123)+K123) -> 453.4748 | S123: =R123-(C123-F123) -> 73.8448 | T123: =(M123-(M123*N123)-O123-(C123*E123)+P123) -> 468.0248 | U123: =T123-(C123-F123) -> 88.3948
A124: NAUTIKA | B124: NTK-KIT-QUICK | C124: 0 | E124: 0.04 | F124: 0 | H124: 109.9 | I124: 0.12 | J124: {=IF(H124<12.5, H124/2, IF(H124<29, 6.25, IF(H124<50, 6.5, IF(H124<79, 6.75, VALUE(SUBSTITUTE( INDEX(RESUMO!$J$2:$J$100, MATCH(1, (D124>=RESUMO!$H$2:$H$100)*(D124<=RESUMO!$I$2:$I$100)*(H124>=RESUMO!$K$2:$K$100)*(H124<=RESUMO!$L$2:$L$100), 0)), "R$ ", "")) ))))} -> 13.97 | K124: 0 | L124: =S124/H124 -> 0.75288444 | O124: {=IF(M124<12.5, 0, IF(M124<29, 6.25, IF(M124<50, 6.5, IF(M124<79, 6.75, VALUE(SUBSTITUTE( INDEX(RESUMO!$J$2:$J$100, MATCH(1, (D124>=RESUMO!$H$2:$H$100)*(D124<=RESUMO!$I$2:$I$100)*(M124>=RESUMO!$K$2:$K$100)*(M124<=RESUMO!$L$2:$L$100), 0)), "R$ ", "")) ))))} -> 0 | Q124: =U124/M124 -> #DIV/0! | R124: =(H124-(H124*I124)-J124-(C124*E124)+K124) -> 82.742 | S124: =R124-(C124-F124) -> 82.742 | T124: =(M124-(M124*N124)-O124-(C124*E124)+P124) -> 0 | U124: =T124-(C124-F124) -> 0
A125: NAUTIKA | B125: NTK-EXTERMINATOR | C125: 0 | E125: 0.04 | F125: 0 | H125: 119.9 | I125: 0.115 | J125: {=IF(H125<12.5, H125/2, IF(H125<29, 6.25, IF(H125<50, 6.5, IF(H125<79, 6.75, VALUE(SUBSTITUTE( INDEX(RESUMO!$J$2:$J$100, MATCH(1, (D125>=RESUMO!$H$2:$H$100)*(D125<=RESUMO!$I$2:$I$100)*(H125>=RESUMO!$K$2:$K$100)*(H125<=RESUMO!$L$2:$L$100), 0)), "R$ ", "")) ))))} -> 13.97 | K125: 0 | L125: =S125/H125 -> 0.76848624 | O125: {=IF(M125<12.5, 0, IF(M125<29, 6.25, IF(M125<50, 6.5, IF(M125<79, 6.75, VALUE(SUBSTITUTE( INDEX(RESUMO!$J$2:$J$100, MATCH(1, (D125>=RESUMO!$H$2:$H$100)*(D125<=RESUMO!$I$2:$I$100)*(M125>=RESUMO!$K$2:$K$100)*(M125<=RESUMO!$L$2:$L$100), 0)), "R$ ", "")) ))))} -> 0 | Q125: =U125/M125 -> #DIV/0! | R125: =(H125-(H125*I125)-J125-(C125*E125)+K125) -> 92.1415 | S125: =R125-(C125-F125) -> 92.1415 | T125: =(M125-(M125*N125)-O125-(C125*E125)+P125) -> 0 | U125: =T125-(C125-F125) -> 0
A126: NAUTIKA | B126: NTK-BUSSOLA | C126: 0 | E126: 0.04 | F126: 0 | H126: 45 | I126: 0.115 | J126: {=IF(H126<12.5, H126/2, IF(H126<29, 6.25, IF(H126<50, 6.5, IF(H126<79, 6.75, VALUE(SUBSTITUTE( INDEX(RESUMO!$J$2:$J$100, MATCH(1, (D126>=RESUMO!$H$2:$H$100)*(D126<=RESUMO!$I$2:$I$100)*(H126>=RESUMO!$K$2:$K$100)*(H126<=RESUMO!$L$2:$L$100), 0)), "R$ ", "")) ))))} -> 6.5 | K126: 0 | L126: =S126/H126 -> 0.74055556 | O126: {=IF(M126<12.5, 0, IF(M126<29, 6.25, IF(M126<50, 6.5, IF(M126<79, 6.75, VALUE(SUBSTITUTE( INDEX(RESUMO!$J$2:$J$100, MATCH(1, (D126>=RESUMO!$H$2:$H$100)*(D126<=RESUMO!$I$2:$I$100)*(M126>=RESUMO!$K$2:$K$100)*(M126<=RESUMO!$L$2:$L$100), 0)), "R$ ", "")) ))))} -> 0 | Q126: =U126/M126 -> #DIV/0! | R126: =(H126-(H126*I126)-J126-(C126*E126)+K126) -> 33.325 | S126: =R126-(C126-F126) -> 33.325 | T126: =(M126-(M126*N126)-O126-(C126*E126)+P126) -> 0 | U126: =T126-(C126-F126) -> 0
A127: NAUTIKA | B127: NTK-LANTERNA-APUS | C127: 0 | E127: 0.04 | F127: 0 | H127: 54.9 | I127: 0.115 | J127: {=IF(H127<12.5, H127/2, IF(H127<29, 6.25, IF(H127<50, 6.5, IF(H127<79, 6.75, VALUE(SUBSTITUTE( INDEX(RESUMO!$J$2:$J$100, MATCH(1, (D127>=RESUMO!$H$2:$H$100)*(D127<=RESUMO!$I$2:$I$100)*(H127>=RESUMO!$K$2:$K$100)*(H127<=RESUMO!$L$2:$L$100), 0)), "R$ ", "")) ))))} -> 6.75 | K127: 0 | L127: =S127/H127 -> 0.76204918 | O127: {=IF(M127<12.5, 0, IF(M127<29, 6.25, IF(M127<50, 6.5, IF(M127<79, 6.75, VALUE(SUBSTITUTE( INDEX(RESUMO!$J$2:$J$100, MATCH(1, (D127>=RESUMO!$H$2:$H$100)*(D127<=RESUMO!$I$2:$I$100)*(M127>=RESUMO!$K$2:$K$100)*(M127<=RESUMO!$L$2:$L$100), 0)), "R$ ", "")) ))))} -> 0 | Q127: =U127/M127 -> #DIV/0! | R127: =(H127-(H127*I127)-J127-(C127*E127)+K127) -> 41.8365 | S127: =R127-(C127-F127) -> 41.8365 | T127: =(M127-(M127*N127)-O127-(C127*E127)+P127) -> 0 | U127: =T127-(C127-F127) -> 0
B128: KABABY-PROTETOR-BRANCO | C128: 0 | E128: 0.04 | F128: 0 | H128: 14.9 | I128: 0.115 | J128: {=IF(H128<12.5, H128/2, IF(H128<29, 6.25, IF(H128<50, 6.5, IF(H128<79, 6.75, VALUE(SUBSTITUTE( INDEX(RESUMO!$J$2:$J$100, MATCH(1, (D128>=RESUMO!$H$2:$H$100)*(D128<=RESUMO!$I$2:$I$100)*(H128>=RESUMO!$K$2:$K$100)*(H128<=RESUMO!$L$2:$L$100), 0)), "R$ ", "")) ))))} -> 6.25 | K128: 0 | L128: =S128/H128 -> 0.46553691 | O128: {=IF(M128<12.5, 0, IF(M128<29, 6.25, IF(M128<50, 6.5, IF(M128<79, 6.75, VALUE(SUBSTITUTE( INDEX(RESUMO!$J$2:$J$100, MATCH(1, (D128>=RESUMO!$H$2:$H$100)*(D128<=RESUMO!$I$2:$I$100)*(M128>=RESUMO!$K$2:$K$100)*(M128<=RESUMO!$L$2:$L$100), 0)), "R$ ", "")) ))))} -> 0 | Q128: =U128/M128 -> #DIV/0! | R128: =(H128-(H128*I128)-J128-(C128*E128)+K128) -> 6.9365 | S128: =R128-(C128-F128) -> 6.9365 | T128: =(M128-(M128*N128)-O128-(C128*E128)+P128) -> 0 | U128: =T128-(C128-F128) -> 0
B129: KABABY-SAQUINHO-LEITE | C129: 0 | E129: 0.04 | F129: 0 | H129: 44.9 | I129: 0.115 | J129: {=IF(H129<12.5, H129/2, IF(H129<29, 6.25, IF(H129<50, 6.5, IF(H129<79, 6.75, VALUE(SUBSTITUTE( INDEX(RESUMO!$J$2:$J$100, MATCH(1, (D129>=RESUMO!$H$2:$H$100)*(D129<=RESUMO!$I$2:$I$100)*(H129>=RESUMO!$K$2:$K$100)*(H129<=RESUMO!$L$2:$L$100), 0)), "R$ ", "")) ))))} -> 6.5 | K129: 0 | L129: =S129/H129 -> 0.74023385 | O129: {=IF(M129<12.5, 0, IF(M129<29, 6.25, IF(M129<50, 6.5, IF(M129<79, 6.75, VALUE(SUBSTITUTE( INDEX(RESUMO!$J$2:$J$100, MATCH(1, (D129>=RESUMO!$H$2:$H$100)*(D129<=RESUMO!$I$2:$I$100)*(M129>=RESUMO!$K$2:$K$100)*(M129<=RESUMO!$L$2:$L$100), 0)), "R$ ", "")) ))))} -> 0 | Q129: =U129/M129 -> #DIV/0! | R129: =(H129-(H129*I129)-J129-(C129*E129)+K129) -> 33.2365 | S129: =R129-(C129-F129) -> 33.2365 | T129: =(M129-(M129*N129)-O129-(C129*E129)+P129) -> 0 | U129: =T129-(C129-F129) -> 0
...
